{
"meta":{"test_sets":[],"test_metrics":[],"learn_metrics":[{"best_value":"Min","name":"RMSE"}],"launch_mode":"Train","parameters":"","iteration_count":1000,"learn_sets":["learn"],"name":"experiment"},
"iterations":[
{"learn":[15.71672155],"iteration":0,"passed_time":0.006303852274,"remaining_time":6.297548422},
{"learn":[15.13875952],"iteration":1,"passed_time":0.01263528171,"remaining_time":6.305005575},
{"learn":[14.60073708],"iteration":2,"passed_time":0.0166526817,"remaining_time":5.534241218},
{"learn":[14.09087254],"iteration":3,"passed_time":0.02059588586,"remaining_time":5.128375579},
{"learn":[13.59295443],"iteration":4,"passed_time":0.02719765231,"remaining_time":5.412332809},
{"learn":[13.09455427],"iteration":5,"passed_time":0.03208956259,"remaining_time":5.316170869},
{"learn":[12.63123744],"iteration":6,"passed_time":0.03616800989,"remaining_time":5.130690546},
{"learn":[12.18429802],"iteration":7,"passed_time":0.04198325495,"remaining_time":5.205923613},
{"learn":[11.75692574],"iteration":8,"passed_time":0.05060514089,"remaining_time":5.572188291},
{"learn":[11.35037531],"iteration":9,"passed_time":0.06407829832,"remaining_time":6.343751534},
{"learn":[10.9726343],"iteration":10,"passed_time":0.07603345445,"remaining_time":6.836098769},
{"learn":[10.60584823],"iteration":11,"passed_time":0.09359146743,"remaining_time":7.705697485},
{"learn":[10.22806729],"iteration":12,"passed_time":0.1014717176,"remaining_time":7.704045024},
{"learn":[9.881591189],"iteration":13,"passed_time":0.1113969619,"remaining_time":7.84552889},
{"learn":[9.548160853],"iteration":14,"passed_time":0.1237597298,"remaining_time":8.126888922},
{"learn":[9.228430938],"iteration":15,"passed_time":0.1320666307,"remaining_time":8.122097789},
{"learn":[8.909943496],"iteration":16,"passed_time":0.1437965207,"remaining_time":8.314822346},
{"learn":[8.603942103],"iteration":17,"passed_time":0.1506719454,"remaining_time":8.219991687},
{"learn":[8.317618808],"iteration":18,"passed_time":0.1590862632,"remaining_time":8.213874956},
{"learn":[8.045560662],"iteration":19,"passed_time":0.1657645296,"remaining_time":8.122461951},
{"learn":[7.779364824],"iteration":20,"passed_time":0.1771696303,"remaining_time":8.259479431},
{"learn":[7.532990505],"iteration":21,"passed_time":0.1892162024,"remaining_time":8.411520269},
{"learn":[7.290820806],"iteration":22,"passed_time":0.2049323778,"remaining_time":8.705171006},
{"learn":[7.057066187],"iteration":23,"passed_time":0.2135833772,"remaining_time":8.685724007},
{"learn":[6.830968421],"iteration":24,"passed_time":0.2244016361,"remaining_time":8.751663806},
{"learn":[6.621587279],"iteration":25,"passed_time":0.2308520082,"remaining_time":8.648071384},
{"learn":[6.415526728],"iteration":26,"passed_time":0.23971524,"remaining_time":8.638626983},
{"learn":[6.218633714],"iteration":27,"passed_time":0.2481546036,"remaining_time":8.614509811},
{"learn":[6.041109176],"iteration":28,"passed_time":0.2566746831,"remaining_time":8.594176459},
{"learn":[5.854569409],"iteration":29,"passed_time":0.2624948461,"remaining_time":8.487333356},
{"learn":[5.674475542],"iteration":30,"passed_time":0.2717466067,"remaining_time":8.494272963},
{"learn":[5.50488476],"iteration":31,"passed_time":0.2783861326,"remaining_time":8.42118051},
{"learn":[5.342293333],"iteration":32,"passed_time":0.2867253568,"remaining_time":8.401921819},
{"learn":[5.188260145],"iteration":33,"passed_time":0.2919584293,"remaining_time":8.295054197},
{"learn":[5.03765532],"iteration":34,"passed_time":0.3005000207,"remaining_time":8.285214857},
{"learn":[4.897245354],"iteration":35,"passed_time":0.3066748234,"remaining_time":8.212070271},
{"learn":[4.758741093],"iteration":36,"passed_time":0.3153189942,"remaining_time":8.206815983},
{"learn":[4.62854288],"iteration":37,"passed_time":0.3214922451,"remaining_time":8.138829994},
{"learn":[4.506414614],"iteration":38,"passed_time":0.3264813025,"remaining_time":8.044834147},
{"learn":[4.384791459],"iteration":39,"passed_time":0.3347627078,"remaining_time":8.034304987},
{"learn":[4.275671004],"iteration":40,"passed_time":0.3405907024,"remaining_time":7.966499601},
{"learn":[4.165594805],"iteration":41,"passed_time":0.3484426855,"remaining_time":7.947811731},
{"learn":[4.063942125],"iteration":42,"passed_time":0.3535357532,"remaining_time":7.868225949},
{"learn":[3.961781882],"iteration":43,"passed_time":0.3632371194,"remaining_time":7.892151957},
{"learn":[3.863711852],"iteration":44,"passed_time":0.3750402346,"remaining_time":7.959187201},
{"learn":[3.775787135],"iteration":45,"passed_time":0.3819990618,"remaining_time":7.922328369},
{"learn":[3.687698341],"iteration":46,"passed_time":0.3867639281,"remaining_time":7.842255819},
{"learn":[3.602530698],"iteration":47,"passed_time":0.4342905688,"remaining_time":8.613429614},
{"learn":[3.52249635],"iteration":48,"passed_time":0.4491281788,"remaining_time":8.716753021},
{"learn":[3.439253012],"iteration":49,"passed_time":0.4635584227,"remaining_time":8.807610032},
{"learn":[3.367251654],"iteration":50,"passed_time":0.5082655007,"remaining_time":9.457724709},
{"learn":[3.303235333],"iteration":51,"passed_time":0.5202386519,"remaining_time":9.484350807},
{"learn":[3.23530213],"iteration":52,"passed_time":0.5338092216,"remaining_time":9.538062884},
{"learn":[3.170208587],"iteration":53,"passed_time":0.5683768686,"remaining_time":9.957120699},
{"learn":[3.111317053],"iteration":54,"passed_time":0.5823783774,"remaining_time":10.00631939},
{"learn":[3.049576391],"iteration":55,"passed_time":0.5989969903,"remaining_time":10.09737784},
{"learn":[2.989841309],"iteration":56,"passed_time":0.6143475773,"remaining_time":10.1636801},
{"learn":[2.935106459],"iteration":57,"passed_time":0.6291041055,"remaining_time":10.2175184},
{"learn":[2.881516376],"iteration":58,"passed_time":0.6403151105,"remaining_time":10.21248337},
{"learn":[2.82839364],"iteration":59,"passed_time":0.6466635294,"remaining_time":10.13106196},
{"learn":[2.776127265],"iteration":60,"passed_time":0.6551538893,"remaining_time":10.0850738},
{"learn":[2.730207589],"iteration":61,"passed_time":0.6878323663,"remaining_time":10.40623806},
{"learn":[2.686910367],"iteration":62,"passed_time":0.6982323278,"remaining_time":10.38482049},
{"learn":[2.639991924],"iteration":63,"passed_time":0.7059778796,"remaining_time":10.32492649},
{"learn":[2.598958267],"iteration":64,"passed_time":0.7127402885,"remaining_time":10.25249492},
{"learn":[2.559519838],"iteration":65,"passed_time":0.7199607073,"remaining_time":10.18853486},
{"learn":[2.520734391],"iteration":66,"passed_time":0.7250217014,"remaining_time":10.09619772},
{"learn":[2.481129141],"iteration":67,"passed_time":0.730053546,"remaining_time":10.00602801},
{"learn":[2.441263228],"iteration":68,"passed_time":0.7362732449,"remaining_time":9.934353492},
{"learn":[2.407073023],"iteration":69,"passed_time":0.7409503599,"remaining_time":9.844054782},
{"learn":[2.375514914],"iteration":70,"passed_time":0.7461095866,"remaining_time":9.76247614},
{"learn":[2.340661661],"iteration":71,"passed_time":0.7523781628,"remaining_time":9.697318543},
{"learn":[2.307396424],"iteration":72,"passed_time":0.7574692279,"remaining_time":9.618821565},
{"learn":[2.276908333],"iteration":73,"passed_time":0.7625346281,"remaining_time":9.541987373},
{"learn":[2.247864862],"iteration":74,"passed_time":0.7691875761,"remaining_time":9.486646772},
{"learn":[2.221332469],"iteration":75,"passed_time":0.7742272634,"remaining_time":9.412973571},
{"learn":[2.194260009],"iteration":76,"passed_time":0.7792185037,"remaining_time":9.340502324},
{"learn":[2.169500122],"iteration":77,"passed_time":0.7860589479,"remaining_time":9.291619871},
{"learn":[2.143601375],"iteration":78,"passed_time":0.7908571351,"remaining_time":9.219992676},
{"learn":[2.119936731],"iteration":79,"passed_time":0.7959170012,"remaining_time":9.153045514},
{"learn":[2.099303897],"iteration":80,"passed_time":0.8055514755,"remaining_time":9.139528469},
{"learn":[2.078725734],"iteration":81,"passed_time":0.8153142944,"remaining_time":9.127542955},
{"learn":[2.056444768],"iteration":82,"passed_time":0.8218915728,"remaining_time":9.080416533},
{"learn":[2.03357841],"iteration":83,"passed_time":0.8282144575,"remaining_time":9.031481466},
{"learn":[2.013857342],"iteration":84,"passed_time":0.8372493259,"remaining_time":9.012742744},
{"learn":[1.995696372],"iteration":85,"passed_time":0.8422966802,"remaining_time":8.951850764},
{"learn":[1.978638479],"iteration":86,"passed_time":0.8487152852,"remaining_time":8.906632821},
{"learn":[1.959811219],"iteration":87,"passed_time":0.8536749262,"remaining_time":8.847176507},
{"learn":[1.943290945],"iteration":88,"passed_time":0.8590326955,"remaining_time":8.793020063},
{"learn":[1.926054524],"iteration":89,"passed_time":0.8657715714,"remaining_time":8.753912555},
{"learn":[1.913026144],"iteration":90,"passed_time":0.8706405673,"remaining_time":8.696838194},
{"learn":[1.897345871],"iteration":91,"passed_time":0.8758669749,"remaining_time":8.644426231},
{"learn":[1.880965288],"iteration":92,"passed_time":0.8821729716,"remaining_time":8.603557906},
{"learn":[1.865224865],"iteration":93,"passed_time":0.8875372545,"remaining_time":8.554348432},
{"learn":[1.851008582],"iteration":94,"passed_time":0.8932011138,"remaining_time":8.508915873},
{"learn":[1.837403338],"iteration":95,"passed_time":0.8985058048,"remaining_time":8.460929662},
{"learn":[1.82249331],"iteration":96,"passed_time":0.9035299151,"remaining_time":8.411211478},
{"learn":[1.806803243],"iteration":97,"passed_time":0.9108240295,"remaining_time":8.38329872},
{"learn":[1.793103064],"iteration":98,"passed_time":0.9174279473,"remaining_time":8.349521016},
{"learn":[1.779843365],"iteration":99,"passed_time":0.9225626154,"remaining_time":8.303063539},
{"learn":[1.767551738],"iteration":100,"passed_time":0.9293477355,"remaining_time":8.272114993},
{"learn":[1.755808073],"iteration":101,"passed_time":0.9360234771,"remaining_time":8.240677279},
{"learn":[1.74423537],"iteration":102,"passed_time":0.9443453175,"remaining_time":8.224055823},
{"learn":[1.73389077],"iteration":103,"passed_time":0.9506237844,"remaining_time":8.189989527},
{"learn":[1.725226413],"iteration":104,"passed_time":0.9587233778,"remaining_time":8.171975458},
{"learn":[1.713542388],"iteration":105,"passed_time":0.9645820372,"remaining_time":8.135248502},
{"learn":[1.704158419],"iteration":106,"passed_time":0.9703764663,"remaining_time":8.098562471},
{"learn":[1.692853768],"iteration":107,"passed_time":0.9783480875,"remaining_time":8.080430501},
{"learn":[1.682351231],"iteration":108,"passed_time":0.9846065144,"remaining_time":8.048480774},
{"learn":[1.672867797],"iteration":109,"passed_time":0.9920348124,"remaining_time":8.026463482},
{"learn":[1.662750924],"iteration":110,"passed_time":0.9983444564,"remaining_time":7.995749745},
{"learn":[1.656225494],"iteration":111,"passed_time":1.006423333,"remaining_time":7.97949928},
{"learn":[1.64700868],"iteration":112,"passed_time":1.014510999,"remaining_time":7.963462446},
{"learn":[1.639567813],"iteration":113,"passed_time":1.022196264,"remaining_time":7.944437632},
{"learn":[1.629451808],"iteration":114,"passed_time":1.029175493,"remaining_time":7.920176619},
{"learn":[1.620903701],"iteration":115,"passed_time":1.036043445,"remaining_time":7.895365566},
{"learn":[1.614926774],"iteration":116,"passed_time":1.043323612,"remaining_time":7.873972216},
{"learn":[1.607196671],"iteration":117,"passed_time":1.049374987,"remaining_time":7.843633379},
{"learn":[1.600140333],"iteration":118,"passed_time":1.057603148,"remaining_time":7.829818263},
{"learn":[1.592230612],"iteration":119,"passed_time":1.063619464,"remaining_time":7.799876066},
{"learn":[1.582560166],"iteration":120,"passed_time":1.071966829,"remaining_time":7.787263163},
{"learn":[1.575745301],"iteration":121,"passed_time":1.080879771,"remaining_time":7.77879048},
{"learn":[1.568244264],"iteration":122,"passed_time":1.088382132,"remaining_time":7.760253085},
{"learn":[1.56261616],"iteration":123,"passed_time":1.094379909,"remaining_time":7.731264519},
{"learn":[1.555012829],"iteration":124,"passed_time":1.10024051,"remaining_time":7.70168357},
{"learn":[1.549091309],"iteration":125,"passed_time":1.107870848,"remaining_time":7.684754932},
{"learn":[1.542912761],"iteration":126,"passed_time":1.114727825,"remaining_time":7.662656621},
{"learn":[1.536576236],"iteration":127,"passed_time":1.12238896,"remaining_time":7.646274792},
{"learn":[1.530847114],"iteration":128,"passed_time":1.129137762,"remaining_time":7.623868144},
{"learn":[1.526342223],"iteration":129,"passed_time":1.135990513,"remaining_time":7.60239805},
{"learn":[1.518699152],"iteration":130,"passed_time":1.140992838,"remaining_time":7.568876155},
{"learn":[1.5123091],"iteration":131,"passed_time":1.145907088,"remaining_time":7.535207215},
{"learn":[1.505491903],"iteration":132,"passed_time":1.15262042,"remaining_time":7.51369853},
{"learn":[1.500070772],"iteration":133,"passed_time":1.1574567,"remaining_time":7.480279867},
{"learn":[1.494111686],"iteration":134,"passed_time":1.161967005,"remaining_time":7.445195995},
{"learn":[1.488515266],"iteration":135,"passed_time":1.16853708,"remaining_time":7.42364733},
{"learn":[1.483848395],"iteration":136,"passed_time":1.173108963,"remaining_time":7.389730181},
{"learn":[1.477522076],"iteration":137,"passed_time":1.178006237,"remaining_time":7.358270845},
{"learn":[1.472691665],"iteration":138,"passed_time":1.18441402,"remaining_time":7.336550155},
{"learn":[1.46782537],"iteration":139,"passed_time":1.189243849,"remaining_time":7.305355072},
{"learn":[1.462319707],"iteration":140,"passed_time":1.194114053,"remaining_time":7.274779937},
{"learn":[1.458571767],"iteration":141,"passed_time":1.200502232,"remaining_time":7.253738838},
{"learn":[1.453397048],"iteration":142,"passed_time":1.205296301,"remaining_time":7.223349158},
{"learn":[1.449238895],"iteration":143,"passed_time":1.210202245,"remaining_time":7.19398001},
{"learn":[1.443357322],"iteration":144,"passed_time":1.218113934,"remaining_time":7.182671817},
{"learn":[1.43711219],"iteration":145,"passed_time":1.223033607,"remaining_time":7.153908907},
{"learn":[1.431922457],"iteration":146,"passed_time":1.229739391,"remaining_time":7.135834699},
{"learn":[1.428575748],"iteration":147,"passed_time":1.234570504,"remaining_time":7.10712209},
{"learn":[1.425559178],"iteration":148,"passed_time":1.239460435,"remaining_time":7.079065972},
{"learn":[1.421603724],"iteration":149,"passed_time":1.246131296,"remaining_time":7.061410676},
{"learn":[1.41810478],"iteration":150,"passed_time":1.251078874,"remaining_time":7.034211683},
{"learn":[1.413166505],"iteration":151,"passed_time":1.256223069,"remaining_time":7.008402387},
{"learn":[1.409957879],"iteration":152,"passed_time":1.262952792,"remaining_time":6.991640617},
{"learn":[1.404727407],"iteration":153,"passed_time":1.268047784,"remaining_time":6.966028735},
{"learn":[1.399994544],"iteration":154,"passed_time":1.272925344,"remaining_time":6.939496233},
{"learn":[1.394946043],"iteration":155,"passed_time":1.280038683,"remaining_time":6.925337493},
{"learn":[1.390644805],"iteration":156,"passed_time":1.285070567,"remaining_time":6.900092281},
{"learn":[1.38341077],"iteration":157,"passed_time":1.291408457,"remaining_time":6.882062791},
{"learn":[1.378908322],"iteration":158,"passed_time":1.296587814,"remaining_time":6.858052524},
{"learn":[1.374193913],"iteration":159,"passed_time":1.301684681,"remaining_time":6.833844578},
{"learn":[1.369997972],"iteration":160,"passed_time":1.309030292,"remaining_time":6.82159264},
{"learn":[1.366419853],"iteration":161,"passed_time":1.315594267,"remaining_time":6.805357998},
{"learn":[1.361864341],"iteration":162,"passed_time":1.320568894,"remaining_time":6.781080764},
{"learn":[1.358706657],"iteration":163,"passed_time":1.328453106,"remaining_time":6.771870713},
{"learn":[1.353742606],"iteration":164,"passed_time":1.334903594,"remaining_time":6.755421219},
{"learn":[1.350537888],"iteration":165,"passed_time":1.341708082,"remaining_time":6.740870725},
{"learn":[1.344777245],"iteration":166,"passed_time":1.346679012,"remaining_time":6.717267168},
{"learn":[1.34048785],"iteration":167,"passed_time":1.351643549,"remaining_time":6.693853768},
{"learn":[1.336295161],"iteration":168,"passed_time":1.358367519,"remaining_time":6.679310107},
{"learn":[1.330922288],"iteration":169,"passed_time":1.363411088,"remaining_time":6.656654133},
{"learn":[1.326846098],"iteration":170,"passed_time":1.36817284,"remaining_time":6.632837919},
{"learn":[1.322993012],"iteration":171,"passed_time":1.374889274,"remaining_time":6.618653015},
{"learn":[1.317001045],"iteration":172,"passed_time":1.379735804,"remaining_time":6.595615664},
{"learn":[1.311887195],"iteration":173,"passed_time":1.384697191,"remaining_time":6.573332644},
{"learn":[1.308807901],"iteration":174,"passed_time":1.391382396,"remaining_time":6.559374152},
{"learn":[1.305998322],"iteration":175,"passed_time":1.396404386,"remaining_time":6.537711442},
{"learn":[1.302194488],"iteration":176,"passed_time":1.401025671,"remaining_time":6.514373602},
{"learn":[1.297705354],"iteration":177,"passed_time":1.4085816,"remaining_time":6.504798173},
{"learn":[1.291622898],"iteration":178,"passed_time":1.414497185,"remaining_time":6.487721727},
{"learn":[1.288118266],"iteration":179,"passed_time":1.421024943,"remaining_time":6.473558074},
{"learn":[1.285546179],"iteration":180,"passed_time":1.425935734,"remaining_time":6.452162242},
{"learn":[1.281020581],"iteration":181,"passed_time":1.430827437,"remaining_time":6.430861776},
{"learn":[1.278052718],"iteration":182,"passed_time":1.437711708,"remaining_time":6.418636423},
{"learn":[1.274078543],"iteration":183,"passed_time":1.442740303,"remaining_time":6.398239604},
{"learn":[1.267970321],"iteration":184,"passed_time":1.448401055,"remaining_time":6.380793835},
{"learn":[1.264643363],"iteration":185,"passed_time":1.455972345,"remaining_time":6.37183596},
{"learn":[1.262361978],"iteration":186,"passed_time":1.461826091,"remaining_time":6.355425733},
{"learn":[1.260405156],"iteration":187,"passed_time":1.469126087,"remaining_time":6.345374377},
{"learn":[1.256438478],"iteration":188,"passed_time":1.475409128,"remaining_time":6.330988373},
{"learn":[1.252762669],"iteration":189,"passed_time":1.480651133,"remaining_time":6.312249566},
{"learn":[1.249776395],"iteration":190,"passed_time":1.487429439,"remaining_time":6.300159246},
{"learn":[1.247218585],"iteration":191,"passed_time":1.493667073,"remaining_time":6.285848931},
{"learn":[1.242175085],"iteration":192,"passed_time":1.501492271,"remaining_time":6.27826043},
{"learn":[1.238876908],"iteration":193,"passed_time":1.5077772,"remaining_time":6.264270223},
{"learn":[1.235262107],"iteration":194,"passed_time":1.513802676,"remaining_time":6.249287972},
{"learn":[1.232468639],"iteration":195,"passed_time":1.522009043,"remaining_time":6.243343215},
{"learn":[1.229353061],"iteration":196,"passed_time":1.529251084,"remaining_time":6.233444774},
{"learn":[1.226251881],"iteration":197,"passed_time":1.536576828,"remaining_time":6.223912202},
{"learn":[1.224616627],"iteration":198,"passed_time":1.54259504,"remaining_time":6.209138828},
{"learn":[1.222681752],"iteration":199,"passed_time":1.549980783,"remaining_time":6.199923131},
{"learn":[1.219880432],"iteration":200,"passed_time":1.556235735,"remaining_time":6.186230609},
{"learn":[1.216552735],"iteration":201,"passed_time":1.56158307,"remaining_time":6.169026188},
{"learn":[1.213932316],"iteration":202,"passed_time":1.570392658,"remaining_time":6.165531767},
{"learn":[1.210966757],"iteration":203,"passed_time":1.576692974,"remaining_time":6.152194154},
{"learn":[1.207285437],"iteration":204,"passed_time":1.585192056,"remaining_time":6.147452118},
{"learn":[1.203991022],"iteration":205,"passed_time":1.591911338,"remaining_time":6.135813603},
{"learn":[1.200360408],"iteration":206,"passed_time":1.599341043,"remaining_time":6.126944188},
{"learn":[1.195036978],"iteration":207,"passed_time":1.605893276,"remaining_time":6.114747473},
{"learn":[1.192552593],"iteration":208,"passed_time":1.613791917,"remaining_time":6.10770051},
{"learn":[1.188886023],"iteration":209,"passed_time":1.621066733,"remaining_time":6.098298663},
{"learn":[1.183966258],"iteration":210,"passed_time":1.626379475,"remaining_time":6.081580122},
{"learn":[1.17830807],"iteration":211,"passed_time":1.633815715,"remaining_time":6.072862185},
{"learn":[1.174318559],"iteration":212,"passed_time":1.63957698,"remaining_time":6.057967528},
{"learn":[1.170420232],"iteration":213,"passed_time":1.646416889,"remaining_time":6.047119974},
{"learn":[1.167894265],"iteration":214,"passed_time":1.651750248,"remaining_time":6.030809044},
{"learn":[1.162878287],"iteration":215,"passed_time":1.657272381,"remaining_time":6.015284937},
{"learn":[1.160037286],"iteration":216,"passed_time":1.663760777,"remaining_time":6.003339578},
{"learn":[1.155753608],"iteration":217,"passed_time":1.668694791,"remaining_time":5.98586847},
{"learn":[1.152933089],"iteration":218,"passed_time":1.673611888,"remaining_time":5.968451529},
{"learn":[1.150970995],"iteration":219,"passed_time":1.679826805,"remaining_time":5.955749581},
{"learn":[1.147525765],"iteration":220,"passed_time":1.684742238,"remaining_time":5.938525807},
{"learn":[1.145307619],"iteration":221,"passed_time":1.689650846,"remaining_time":5.921389003},
{"learn":[1.141621876],"iteration":222,"passed_time":1.69611354,"remaining_time":5.909776773},
{"learn":[1.137964194],"iteration":223,"passed_time":1.701040126,"remaining_time":5.892889008},
{"learn":[1.135422248],"iteration":224,"passed_time":1.705965501,"remaining_time":5.876103394},
{"learn":[1.130791015],"iteration":225,"passed_time":1.712691791,"remaining_time":5.86559047},
{"learn":[1.128237254],"iteration":226,"passed_time":1.717965248,"remaining_time":5.850163597},
{"learn":[1.125019463],"iteration":227,"passed_time":1.723799263,"remaining_time":5.836723821},
{"learn":[1.121107684],"iteration":228,"passed_time":1.7363444,"remaining_time":5.845945556},
{"learn":[1.117039734],"iteration":229,"passed_time":1.743744085,"remaining_time":5.837751938},
{"learn":[1.114569126],"iteration":230,"passed_time":1.751451772,"remaining_time":5.830590532},
{"learn":[1.111244848],"iteration":231,"passed_time":1.765282949,"remaining_time":5.84369528},
{"learn":[1.108830291],"iteration":232,"passed_time":1.773443541,"remaining_time":5.83790213},
{"learn":[1.105462273],"iteration":233,"passed_time":1.785020831,"remaining_time":5.84327332},
{"learn":[1.101131072],"iteration":234,"passed_time":1.79403569,"remaining_time":5.840158735},
{"learn":[1.097788746],"iteration":235,"passed_time":1.799454548,"remaining_time":5.82535286},
{"learn":[1.094930506],"iteration":236,"passed_time":1.805181046,"remaining_time":5.811616615},
{"learn":[1.090747473],"iteration":237,"passed_time":1.810860559,"remaining_time":5.797797251},
{"learn":[1.08789512],"iteration":238,"passed_time":1.816292891,"remaining_time":5.783258954},
{"learn":[1.084499837],"iteration":239,"passed_time":1.823650714,"remaining_time":5.774893927},
{"learn":[1.080079335],"iteration":240,"passed_time":1.830941069,"remaining_time":5.766324777},
{"learn":[1.07662187],"iteration":241,"passed_time":1.836850892,"remaining_time":5.75344205},
{"learn":[1.074323263],"iteration":242,"passed_time":1.842555321,"remaining_time":5.739976863},
{"learn":[1.070725364],"iteration":243,"passed_time":1.84738827,"remaining_time":5.72387513},
{"learn":[1.068833065],"iteration":244,"passed_time":1.853698621,"remaining_time":5.712418199},
{"learn":[1.065643126],"iteration":245,"passed_time":1.858618654,"remaining_time":5.696741728},
{"learn":[1.063120263],"iteration":246,"passed_time":1.863488356,"remaining_time":5.680998915},
{"learn":[1.059811348],"iteration":247,"passed_time":1.870022487,"remaining_time":5.670390766},
{"learn":[1.058710511],"iteration":248,"passed_time":1.87553306,"remaining_time":5.656728224},
{"learn":[1.05413074],"iteration":249,"passed_time":1.880395601,"remaining_time":5.641186804},
{"learn":[1.052585562],"iteration":250,"passed_time":1.886558424,"remaining_time":5.629610596},
{"learn":[1.048737085],"iteration":251,"passed_time":1.891606736,"remaining_time":5.614769201},
{"learn":[1.044679227],"iteration":252,"passed_time":1.896514377,"remaining_time":5.599589879},
{"learn":[1.041304631],"iteration":253,"passed_time":1.903094737,"remaining_time":5.589404227},
{"learn":[1.038470807],"iteration":254,"passed_time":1.908882625,"remaining_time":5.57693159},
{"learn":[1.036411722],"iteration":255,"passed_time":1.914509757,"remaining_time":5.56404398},
{"learn":[1.032962123],"iteration":256,"passed_time":1.922538509,"remaining_time":5.558156079},
{"learn":[1.032188554],"iteration":257,"passed_time":1.92868579,"remaining_time":5.546840527},
{"learn":[1.029079027],"iteration":258,"passed_time":1.934981275,"remaining_time":5.535988897},
{"learn":[1.027550202],"iteration":259,"passed_time":1.940337797,"remaining_time":5.522499883},
{"learn":[1.025803609],"iteration":260,"passed_time":1.945880822,"remaining_time":5.509601256},
{"learn":[1.02323966],"iteration":261,"passed_time":1.952681562,"remaining_time":5.500301499},
{"learn":[1.021648873],"iteration":262,"passed_time":1.957605224,"remaining_time":5.485760646},
{"learn":[1.019406057],"iteration":263,"passed_time":1.963187041,"remaining_time":5.473127509},
{"learn":[1.017692626],"iteration":264,"passed_time":1.971515923,"remaining_time":5.468166806},
{"learn":[1.012763947],"iteration":265,"passed_time":1.97769427,"remaining_time":5.457246594},
{"learn":[1.010038539],"iteration":266,"passed_time":1.985623509,"remaining_time":5.451168659},
{"learn":[1.005905636],"iteration":267,"passed_time":1.991989092,"remaining_time":5.440806029},
{"learn":[1.002597715],"iteration":268,"passed_time":1.99927603,"remaining_time":5.432976869},
{"learn":[0.9982527476],"iteration":269,"passed_time":2.005921919,"remaining_time":5.423418521},
{"learn":[0.9937893076],"iteration":270,"passed_time":2.013073362,"remaining_time":5.415241627},
{"learn":[0.9905134102],"iteration":271,"passed_time":2.019982432,"remaining_time":5.406423568},
{"learn":[0.9886820217],"iteration":272,"passed_time":2.026197676,"remaining_time":5.395771832},
{"learn":[0.9865872914],"iteration":273,"passed_time":2.033584801,"remaining_time":5.388257538},
{"learn":[0.9845994755],"iteration":274,"passed_time":2.039485934,"remaining_time":5.376826552},
{"learn":[0.9820411649],"iteration":275,"passed_time":2.046884032,"remaining_time":5.369362462},
{"learn":[0.9784771335],"iteration":276,"passed_time":2.052710344,"remaining_time":5.357796314},
{"learn":[0.9754197974],"iteration":277,"passed_time":2.059114126,"remaining_time":5.347771219},
{"learn":[0.9725004629],"iteration":278,"passed_time":2.066345028,"remaining_time":5.339909553},
{"learn":[0.9694247948],"iteration":279,"passed_time":2.071584892,"remaining_time":5.326932579},
{"learn":[0.9670512241],"iteration":280,"passed_time":2.079016022,"remaining_time":5.319617509},
{"learn":[0.9642414369],"iteration":281,"passed_time":2.085656716,"remaining_time":5.310289085},
{"learn":[0.9620698791],"iteration":282,"passed_time":2.091768167,"remaining_time":5.299638784},
{"learn":[0.9598271521],"iteration":283,"passed_time":2.098683323,"remaining_time":5.291046687},
{"learn":[0.9568096481],"iteration":284,"passed_time":2.103376076,"remaining_time":5.276890857},
{"learn":[0.9540879817],"iteration":285,"passed_time":2.109130622,"remaining_time":5.265451972},
{"learn":[0.9521435158],"iteration":286,"passed_time":2.115673735,"remaining_time":5.256011752},
{"learn":[0.9498279553],"iteration":287,"passed_time":2.121035764,"remaining_time":5.243671751},
{"learn":[0.9473314456],"iteration":288,"passed_time":2.130222709,"remaining_time":5.240790125},
{"learn":[0.9449038252],"iteration":289,"passed_time":2.138650446,"remaining_time":5.236006263},
{"learn":[0.9426949862],"iteration":290,"passed_time":2.145723114,"remaining_time":5.227895834},
{"learn":[0.9411344193],"iteration":291,"passed_time":2.150585923,"remaining_time":5.21443436},
{"learn":[0.9390974695],"iteration":292,"passed_time":2.155428466,"remaining_time":5.200982681},
{"learn":[0.9369146759],"iteration":293,"passed_time":2.161695478,"remaining_time":5.191010229},
{"learn":[0.9343924402],"iteration":294,"passed_time":2.16667744,"remaining_time":5.177991849},
{"learn":[0.9323610925],"iteration":295,"passed_time":2.171567331,"remaining_time":5.164808787},
{"learn":[0.9306907614],"iteration":296,"passed_time":2.178282,"remaining_time":5.156000829},
{"learn":[0.9289189737],"iteration":297,"passed_time":2.184097748,"remaining_time":5.145089326},
{"learn":[0.9265344777],"iteration":298,"passed_time":2.189737187,"remaining_time":5.133798556},
{"learn":[0.9251014555],"iteration":299,"passed_time":2.195334434,"remaining_time":5.122447013},
{"learn":[0.9236122906],"iteration":300,"passed_time":2.20035642,"remaining_time":5.109797798},
{"learn":[0.9203978454],"iteration":301,"passed_time":2.206894629,"remaining_time":5.10070348},
{"learn":[0.9197952843],"iteration":302,"passed_time":2.211977948,"remaining_time":5.088279306},
{"learn":[0.9181813009],"iteration":303,"passed_time":2.216827729,"remaining_time":5.075368747},
{"learn":[0.9176497901],"iteration":304,"passed_time":2.223417926,"remaining_time":5.066476914},
{"learn":[0.9144952741],"iteration":305,"passed_time":2.230415424,"remaining_time":5.05852387},
{"learn":[0.9110572787],"iteration":306,"passed_time":2.235482253,"remaining_time":5.046218897},
{"learn":[0.9104673857],"iteration":307,"passed_time":2.242919213,"remaining_time":5.039286024},
{"learn":[0.9083238565],"iteration":308,"passed_time":2.247848834,"remaining_time":5.026742862},
{"learn":[0.9041910389],"iteration":309,"passed_time":2.253764137,"remaining_time":5.016442757},
{"learn":[0.9015264369],"iteration":310,"passed_time":2.260532044,"remaining_time":5.008059738},
{"learn":[0.8983830225],"iteration":311,"passed_time":2.265519386,"remaining_time":4.995760697},
{"learn":[0.8969027387],"iteration":312,"passed_time":2.273790844,"remaining_time":4.990716644},
{"learn":[0.8945236164],"iteration":313,"passed_time":2.278797427,"remaining_time":4.97851922},
{"learn":[0.8927434215],"iteration":314,"passed_time":2.28373156,"remaining_time":4.966209901},
{"learn":[0.8908063511],"iteration":315,"passed_time":2.290530936,"remaining_time":4.957984684},
{"learn":[0.8885938719],"iteration":316,"passed_time":2.296478179,"remaining_time":4.94793248},
{"learn":[0.88733021],"iteration":317,"passed_time":2.302851094,"remaining_time":4.938819013},
{"learn":[0.8855861561],"iteration":318,"passed_time":2.308776363,"remaining_time":4.928767094},
{"learn":[0.8835926076],"iteration":319,"passed_time":2.314655784,"remaining_time":4.918643541},
{"learn":[0.8812548131],"iteration":320,"passed_time":2.323451466,"remaining_time":4.914715096},
{"learn":[0.8795800492],"iteration":321,"passed_time":2.330238647,"remaining_time":4.906527337},
{"learn":[0.8777412822],"iteration":322,"passed_time":2.338637202,"remaining_time":4.901725653},
{"learn":[0.8769367507],"iteration":323,"passed_time":2.344680641,"remaining_time":4.891988004},
{"learn":[0.8747392709],"iteration":324,"passed_time":2.354792088,"remaining_time":4.89072203},
{"learn":[0.8725612521],"iteration":325,"passed_time":2.361181331,"remaining_time":4.881706187},
{"learn":[0.8708285234],"iteration":326,"passed_time":2.369304855,"remaining_time":4.876275742},
{"learn":[0.8688112596],"iteration":327,"passed_time":2.376172139,"remaining_time":4.868255114},
{"learn":[0.8662406312],"iteration":328,"passed_time":2.384588304,"remaining_time":4.863400462},
{"learn":[0.8638897802],"iteration":329,"passed_time":2.391141866,"remaining_time":4.854742577},
{"learn":[0.8611021252],"iteration":330,"passed_time":2.398758996,"remaining_time":4.848247034},
{"learn":[0.8586141295],"iteration":331,"passed_time":2.408665787,"remaining_time":4.846351644},
{"learn":[0.8564574776],"iteration":332,"passed_time":2.415858686,"remaining_time":4.838972203},
{"learn":[0.8543687108],"iteration":333,"passed_time":2.421532534,"remaining_time":4.828564873},
{"learn":[0.8525610649],"iteration":334,"passed_time":2.428935003,"remaining_time":4.821617244},
{"learn":[0.8501909246],"iteration":335,"passed_time":2.437375666,"remaining_time":4.816718578},
{"learn":[0.8494852792],"iteration":336,"passed_time":2.445606327,"remaining_time":4.811385742},
{"learn":[0.8473745895],"iteration":337,"passed_time":2.453369868,"remaining_time":4.805120866},
{"learn":[0.8453365315],"iteration":338,"passed_time":2.460706809,"remaining_time":4.798015342},
{"learn":[0.843454446],"iteration":339,"passed_time":2.475222795,"remaining_time":4.80484425},
{"learn":[0.8411833092],"iteration":340,"passed_time":2.482516436,"remaining_time":4.797590415},
{"learn":[0.8395404668],"iteration":341,"passed_time":2.488275677,"remaining_time":4.787384198},
{"learn":[0.8374179318],"iteration":342,"passed_time":2.494360315,"remaining_time":4.777827192},
{"learn":[0.835413283],"iteration":343,"passed_time":2.5010651,"remaining_time":4.769472981},
{"learn":[0.8328204417],"iteration":344,"passed_time":2.506559283,"remaining_time":4.758829943},
{"learn":[0.8305679428],"iteration":345,"passed_time":2.513246378,"remaining_time":4.750471478},
{"learn":[0.828871707],"iteration":346,"passed_time":2.518706363,"remaining_time":4.739813414},
{"learn":[0.8253439419],"iteration":347,"passed_time":2.52375225,"remaining_time":4.728409387},
{"learn":[0.8249253357],"iteration":348,"passed_time":2.533698116,"remaining_time":4.726181873},
{"learn":[0.8230963136],"iteration":349,"passed_time":2.541680588,"remaining_time":4.720263949},
{"learn":[0.8209450299],"iteration":350,"passed_time":2.547381101,"remaining_time":4.710114913},
{"learn":[0.8204523603],"iteration":351,"passed_time":2.553256532,"remaining_time":4.700313161},
{"learn":[0.8200504875],"iteration":352,"passed_time":2.559460987,"remaining_time":4.69113671},
{"learn":[0.8180352545],"iteration":353,"passed_time":2.564578803,"remaining_time":4.679994087},
{"learn":[0.8158199643],"iteration":354,"passed_time":2.570176839,"remaining_time":4.669757919},
{"learn":[0.8144363955],"iteration":355,"passed_time":2.576251565,"remaining_time":4.660410135},
{"learn":[0.8121741818],"iteration":356,"passed_time":2.581675628,"remaining_time":4.649908765},
{"learn":[0.8093217626],"iteration":357,"passed_time":2.586771014,"remaining_time":4.638846343},
{"learn":[0.8077828868],"iteration":358,"passed_time":2.593617566,"remaining_time":4.630943899},
{"learn":[0.8055402561],"iteration":359,"passed_time":2.599042381,"remaining_time":4.620519789},
{"learn":[0.8043402771],"iteration":360,"passed_time":2.604309981,"remaining_time":4.609845091},
{"learn":[0.8020838125],"iteration":361,"passed_time":2.610843614,"remaining_time":4.601431563},
{"learn":[0.8006760652],"iteration":362,"passed_time":2.616422381,"remaining_time":4.591352773},
{"learn":[0.7997810802],"iteration":363,"passed_time":2.621395722,"remaining_time":4.580240877},
{"learn":[0.7976855923],"iteration":364,"passed_time":2.627284741,"remaining_time":4.570755645},
{"learn":[0.7963886631],"iteration":365,"passed_time":2.634263893,"remaining_time":4.563178437},
{"learn":[0.794638512],"iteration":366,"passed_time":2.640339964,"remaining_time":4.554046859},
{"learn":[0.7924346615],"iteration":367,"passed_time":2.646716483,"remaining_time":4.545447874},
{"learn":[0.7903411429],"iteration":368,"passed_time":2.651721733,"remaining_time":4.534516027},
{"learn":[0.7888357361],"iteration":369,"passed_time":2.658116858,"remaining_time":4.525982758},
{"learn":[0.7866553853],"iteration":370,"passed_time":2.663503581,"remaining_time":4.515751355},
{"learn":[0.7845581391],"iteration":371,"passed_time":2.668359242,"remaining_time":4.504649473},
{"learn":[0.7833871998],"iteration":372,"passed_time":2.67666053,"remaining_time":4.499373063},
{"learn":[0.7816694945],"iteration":373,"passed_time":2.682138022,"remaining_time":4.489354015},
{"learn":[0.7803470317],"iteration":374,"passed_time":2.688456827,"remaining_time":4.480761378},
{"learn":[0.7782462018],"iteration":375,"passed_time":2.693743802,"remaining_time":4.470468437},
{"learn":[0.7766178886],"iteration":376,"passed_time":2.699378474,"remaining_time":4.460776629},
{"learn":[0.7750448366],"iteration":377,"passed_time":2.705834476,"remaining_time":4.452457788},
{"learn":[0.7738230315],"iteration":378,"passed_time":2.711064765,"remaining_time":4.442140419},
{"learn":[0.7724199347],"iteration":379,"passed_time":2.71629791,"remaining_time":4.431854485},
{"learn":[0.7707084742],"iteration":380,"passed_time":2.722392806,"remaining_time":4.422995137},
{"learn":[0.7690309908],"iteration":381,"passed_time":2.727483252,"remaining_time":4.412525261},
{"learn":[0.7675152964],"iteration":382,"passed_time":2.732520659,"remaining_time":4.401998033},
{"learn":[0.7665396654],"iteration":383,"passed_time":2.739080563,"remaining_time":4.393941737},
{"learn":[0.7643972186],"iteration":384,"passed_time":2.744837333,"remaining_time":4.384610285},
{"learn":[0.7625023511],"iteration":385,"passed_time":2.751961005,"remaining_time":4.377471651},
{"learn":[0.7621075476],"iteration":386,"passed_time":2.756985775,"remaining_time":4.367008475},
{"learn":[0.7611225665],"iteration":387,"passed_time":2.762509874,"remaining_time":4.357360936},
{"learn":[0.75922047],"iteration":388,"passed_time":2.768973104,"remaining_time":4.349209682},
{"learn":[0.7576734951],"iteration":389,"passed_time":2.774576048,"remaining_time":4.339721511},
{"learn":[0.7561484775],"iteration":390,"passed_time":2.780062385,"remaining_time":4.330071592},
{"learn":[0.7539723855],"iteration":391,"passed_time":2.786793119,"remaining_time":4.322373001},
{"learn":[0.7530240417],"iteration":392,"passed_time":2.792433842,"remaining_time":4.312995782},
{"learn":[0.7514387037],"iteration":393,"passed_time":2.798295062,"remaining_time":4.303976669},
{"learn":[0.7498196762],"iteration":394,"passed_time":2.803463434,"remaining_time":4.293912348},
{"learn":[0.7471871412],"iteration":395,"passed_time":2.808753509,"remaining_time":4.284058382},
{"learn":[0.7458490943],"iteration":396,"passed_time":2.814669668,"remaining_time":4.275178362},
{"learn":[0.7444688529],"iteration":397,"passed_time":2.819787256,"remaining_time":4.265105347},
{"learn":[0.7418429215],"iteration":398,"passed_time":2.824989688,"remaining_time":4.255184968},
{"learn":[0.7401590022],"iteration":399,"passed_time":2.830995853,"remaining_time":4.246493779},
{"learn":[0.7377197259],"iteration":400,"passed_time":2.835992572,"remaining_time":4.236308107},
{"learn":[0.7355692022],"iteration":401,"passed_time":2.841591593,"remaining_time":4.227044211},
{"learn":[0.7335496058],"iteration":402,"passed_time":2.847487123,"remaining_time":4.218237748},
{"learn":[0.73243132],"iteration":403,"passed_time":2.852359872,"remaining_time":4.20793684},
{"learn":[0.7317581651],"iteration":404,"passed_time":2.85982922,"remaining_time":4.201477496},
{"learn":[0.7304275962],"iteration":405,"passed_time":2.869214813,"remaining_time":4.197816746},
{"learn":[0.7289065436],"iteration":406,"passed_time":2.875518333,"remaining_time":4.189637277},
{"learn":[0.7274347252],"iteration":407,"passed_time":2.883842394,"remaining_time":4.184398767},
{"learn":[0.7256736388],"iteration":408,"passed_time":2.892065591,"remaining_time":4.178999424},
{"learn":[0.7247654111],"iteration":409,"passed_time":2.900724013,"remaining_time":4.174212603},
{"learn":[0.7235072374],"iteration":410,"passed_time":2.907213516,"remaining_time":4.166298688},
{"learn":[0.721298749],"iteration":411,"passed_time":2.913788993,"remaining_time":4.158514388},
{"learn":[0.7203564835],"iteration":412,"passed_time":2.919637378,"remaining_time":4.14970252},
{"learn":[0.718178456],"iteration":413,"passed_time":2.924819232,"remaining_time":4.139961521},
{"learn":[0.7177435288],"iteration":414,"passed_time":2.936143962,"remaining_time":4.13890173},
{"learn":[0.7160978444],"iteration":415,"passed_time":2.941738713,"remaining_time":4.129748578},
{"learn":[0.7149085606],"iteration":416,"passed_time":2.950751919,"remaining_time":4.125391771},
{"learn":[0.7134718292],"iteration":417,"passed_time":2.959046576,"remaining_time":4.120012219},
{"learn":[0.7125301371],"iteration":418,"passed_time":2.967323673,"remaining_time":4.114594402},
{"learn":[0.7110246322],"iteration":419,"passed_time":2.978683191,"remaining_time":4.113419645},
{"learn":[0.7089541755],"iteration":420,"passed_time":2.985780628,"remaining_time":4.106334878},
{"learn":[0.7078546677],"iteration":421,"passed_time":2.992794067,"remaining_time":4.099135001},
{"learn":[0.7056936971],"iteration":422,"passed_time":2.998941366,"remaining_time":4.090754534},
{"learn":[0.7049304522],"iteration":423,"passed_time":3.00480999,"remaining_time":4.082006023},
{"learn":[0.7041649283],"iteration":424,"passed_time":3.012982531,"remaining_time":4.07638813},
{"learn":[0.7025134298],"iteration":425,"passed_time":3.019207288,"remaining_time":4.068133764},
{"learn":[0.7009873608],"iteration":426,"passed_time":3.025326629,"remaining_time":4.059747443},
{"learn":[0.6992046291],"iteration":427,"passed_time":3.030716271,"remaining_time":4.050396511},
{"learn":[0.69801958],"iteration":428,"passed_time":3.035286992,"remaining_time":4.039974062},
{"learn":[0.6965017776],"iteration":429,"passed_time":3.042537501,"remaining_time":4.033131106},
{"learn":[0.6950883845],"iteration":430,"passed_time":3.048844755,"remaining_time":4.025040987},
{"learn":[0.6933847811],"iteration":431,"passed_time":3.05592559,"remaining_time":4.017976238},
{"learn":[0.6912879242],"iteration":432,"passed_time":3.062747739,"remaining_time":4.010572675},
{"learn":[0.6900407612],"iteration":433,"passed_time":3.06945125,"remaining_time":4.003017068},
{"learn":[0.6891591417],"iteration":434,"passed_time":3.077953455,"remaining_time":3.997801614},
{"learn":[0.6884577445],"iteration":435,"passed_time":3.083931044,"remaining_time":3.989305295},
{"learn":[0.6876975482],"iteration":436,"passed_time":3.091988945,"remaining_time":3.983500632},
{"learn":[0.6858536724],"iteration":437,"passed_time":3.098694903,"remaining_time":3.975950994},
{"learn":[0.6846676378],"iteration":438,"passed_time":3.106399103,"remaining_time":3.969680858},
{"learn":[0.683159989],"iteration":439,"passed_time":3.112991079,"remaining_time":3.961988646},
{"learn":[0.682328847],"iteration":440,"passed_time":3.120330093,"remaining_time":3.955248349},
{"learn":[0.6809016161],"iteration":441,"passed_time":3.127513703,"remaining_time":3.948309154},
{"learn":[0.6792037747],"iteration":442,"passed_time":3.133643345,"remaining_time":3.940043664},
{"learn":[0.6781589859],"iteration":443,"passed_time":3.142116783,"remaining_time":3.934722818},
{"learn":[0.676542341],"iteration":444,"passed_time":3.150250994,"remaining_time":3.928964723},
{"learn":[0.6760012434],"iteration":445,"passed_time":3.158150331,"remaining_time":3.922904223},
{"learn":[0.6753612073],"iteration":446,"passed_time":3.164621511,"remaining_time":3.91506867},
{"learn":[0.6748744475],"iteration":447,"passed_time":3.172265506,"remaining_time":3.908684284},
{"learn":[0.6742914498],"iteration":448,"passed_time":3.177697773,"remaining_time":3.899580118},
{"learn":[0.6725362978],"iteration":449,"passed_time":3.184626606,"remaining_time":3.892321407},
{"learn":[0.6712821413],"iteration":450,"passed_time":3.190926771,"remaining_time":3.884298885},
{"learn":[0.6699228951],"iteration":451,"passed_time":3.196092193,"remaining_time":3.874908234},
{"learn":[0.6687460412],"iteration":452,"passed_time":3.202783583,"remaining_time":3.867378852},
{"learn":[0.6671431749],"iteration":453,"passed_time":3.209186891,"remaining_time":3.859506702},
{"learn":[0.6653461741],"iteration":454,"passed_time":3.216309024,"remaining_time":3.852502018},
{"learn":[0.6646500883],"iteration":455,"passed_time":3.221554972,"remaining_time":3.843258563},
{"learn":[0.6628168624],"iteration":456,"passed_time":3.227997252,"remaining_time":3.835454065},
{"learn":[0.6615882015],"iteration":457,"passed_time":3.234655252,"remaining_time":3.827910801},
{"learn":[0.661399197],"iteration":458,"passed_time":3.241315059,"remaining_time":3.820373523},
{"learn":[0.661189184],"iteration":459,"passed_time":3.246401938,"remaining_time":3.810993579},
{"learn":[0.6598570585],"iteration":460,"passed_time":3.253429847,"remaining_time":3.803901708},
{"learn":[0.6588630563],"iteration":461,"passed_time":3.260717552,"remaining_time":3.797112647},
{"learn":[0.6575749666],"iteration":462,"passed_time":3.266962488,"remaining_time":3.789112},
{"learn":[0.6561165405],"iteration":463,"passed_time":3.272419292,"remaining_time":3.780208493},
{"learn":[0.6544929968],"iteration":464,"passed_time":3.278334478,"remaining_time":3.771847195},
{"learn":[0.653332529],"iteration":465,"passed_time":3.285371124,"remaining_time":3.764781502},
{"learn":[0.652239016],"iteration":466,"passed_time":3.290596908,"remaining_time":3.755649148},
{"learn":[0.6508251678],"iteration":467,"passed_time":3.297406833,"remaining_time":3.748334263},
{"learn":[0.6498291559],"iteration":468,"passed_time":3.302880015,"remaining_time":3.739508076},
{"learn":[0.6474069736],"iteration":469,"passed_time":3.309779074,"remaining_time":3.732304063},
{"learn":[0.6456291222],"iteration":470,"passed_time":3.317787299,"remaining_time":3.726347094},
{"learn":[0.6454550226],"iteration":471,"passed_time":3.331008374,"remaining_time":3.726212757},
{"learn":[0.6442795782],"iteration":472,"passed_time":3.3378825,"remaining_time":3.718951538},
{"learn":[0.6431711698],"iteration":473,"passed_time":3.34582047,"remaining_time":3.712872505},
{"learn":[0.6424367937],"iteration":474,"passed_time":3.352177451,"remaining_time":3.705038235},
{"learn":[0.6422090374],"iteration":475,"passed_time":3.358214416,"remaining_time":3.696857887},
{"learn":[0.6411042231],"iteration":476,"passed_time":3.365173893,"remaining_time":3.689698},
{"learn":[0.6395068777],"iteration":477,"passed_time":3.370381082,"remaining_time":3.680625366},
{"learn":[0.6391361257],"iteration":478,"passed_time":3.375273508,"remaining_time":3.671226508},
{"learn":[0.6377989715],"iteration":479,"passed_time":3.382231934,"remaining_time":3.664084596},
{"learn":[0.6368617381],"iteration":480,"passed_time":3.387241923,"remaining_time":3.654841077},
{"learn":[0.6356440213],"iteration":481,"passed_time":3.393371387,"remaining_time":3.646818213},
{"learn":[0.6344270586],"iteration":482,"passed_time":3.398665402,"remaining_time":3.637908929},
{"learn":[0.6336461873],"iteration":483,"passed_time":3.404275197,"remaining_time":3.629351243},
{"learn":[0.6323124819],"iteration":484,"passed_time":3.410455994,"remaining_time":3.621412035},
{"learn":[0.6310908076],"iteration":485,"passed_time":3.415671954,"remaining_time":3.612459638},
{"learn":[0.6294461482],"iteration":486,"passed_time":3.420649768,"remaining_time":3.603271727},
{"learn":[0.6277325124],"iteration":487,"passed_time":3.426637246,"remaining_time":3.595160389},
{"learn":[0.6273114351],"iteration":488,"passed_time":3.431588027,"remaining_time":3.5859744},
{"learn":[0.6264628947],"iteration":489,"passed_time":3.436667726,"remaining_time":3.576939878},
{"learn":[0.6252516196],"iteration":490,"passed_time":3.443646337,"remaining_time":3.56988999},
{"learn":[0.6245351169],"iteration":491,"passed_time":3.448517566,"remaining_time":3.560664479},
{"learn":[0.6242627589],"iteration":492,"passed_time":3.453449571,"remaining_time":3.551519132},
{"learn":[0.6224724381],"iteration":493,"passed_time":3.461453022,"remaining_time":3.545536901},
{"learn":[0.6212664424],"iteration":494,"passed_time":3.469385265,"remaining_time":3.539473857},
{"learn":[0.6204728978],"iteration":495,"passed_time":3.47720979,"remaining_time":3.533293819},
{"learn":[0.6193766881],"iteration":496,"passed_time":3.483079081,"remaining_time":3.525128326},
{"learn":[0.6180608873],"iteration":497,"passed_time":3.490703647,"remaining_time":3.518741427},
{"learn":[0.6163330016],"iteration":498,"passed_time":3.497203611,"remaining_time":3.511220459},
{"learn":[0.616062933],"iteration":499,"passed_time":3.503481019,"remaining_time":3.503481019},
{"learn":[0.6150165453],"iteration":500,"passed_time":3.510517661,"remaining_time":3.496503618},
{"learn":[0.6143693092],"iteration":501,"passed_time":3.515518341,"remaining_time":3.487506243},
{"learn":[0.6141877382],"iteration":502,"passed_time":3.5216274,"remaining_time":3.479619916},
{"learn":[0.612501586],"iteration":503,"passed_time":3.527700974,"remaining_time":3.47170572},
{"learn":[0.6110866994],"iteration":504,"passed_time":3.534571978,"remaining_time":3.464580453},
{"learn":[0.6105981255],"iteration":505,"passed_time":3.542217137,"remaining_time":3.458211988},
{"learn":[0.6097738992],"iteration":506,"passed_time":3.572133341,"remaining_time":3.47349455},
{"learn":[0.6088943681],"iteration":507,"passed_time":3.587848363,"remaining_time":3.474845265},
{"learn":[0.6081512502],"iteration":508,"passed_time":3.599008857,"remaining_time":3.471735459},
{"learn":[0.6079001712],"iteration":509,"passed_time":3.609891543,"remaining_time":3.468327169},
{"learn":[0.6067192937],"iteration":510,"passed_time":3.622926909,"remaining_time":3.466949625},
{"learn":[0.6061957193],"iteration":511,"passed_time":3.630122132,"remaining_time":3.459960157},
{"learn":[0.6048166993],"iteration":512,"passed_time":3.637849611,"remaining_time":3.453475167},
{"learn":[0.603924023],"iteration":513,"passed_time":3.6444901,"remaining_time":3.445957565},
{"learn":[0.6033749744],"iteration":514,"passed_time":3.652909616,"remaining_time":3.440118764},
{"learn":[0.601921158],"iteration":515,"passed_time":3.659553844,"remaining_time":3.432604768},
{"learn":[0.6007710632],"iteration":516,"passed_time":3.668422142,"remaining_time":3.427171943},
{"learn":[0.5997795913],"iteration":517,"passed_time":3.674379065,"remaining_time":3.419016813},
{"learn":[0.598595832],"iteration":518,"passed_time":3.679672167,"remaining_time":3.410254937},
{"learn":[0.596887774],"iteration":519,"passed_time":3.68558446,"remaining_time":3.402077963},
{"learn":[0.5960125641],"iteration":520,"passed_time":3.689487662,"remaining_time":3.392062553},
{"learn":[0.594449054],"iteration":521,"passed_time":3.696008644,"remaining_time":3.384467685},
{"learn":[0.5936729186],"iteration":522,"passed_time":3.705037359,"remaining_time":3.379164092},
{"learn":[0.5929123646],"iteration":523,"passed_time":3.713534781,"remaining_time":3.373363656},
{"learn":[0.5918429234],"iteration":524,"passed_time":3.721164026,"remaining_time":3.366767452},
{"learn":[0.5909489152],"iteration":525,"passed_time":3.727400689,"remaining_time":3.358912408},
{"learn":[0.5900599855],"iteration":526,"passed_time":3.735375739,"remaining_time":3.352623765},
{"learn":[0.5890162021],"iteration":527,"passed_time":3.74311916,"remaining_time":3.346121673},
{"learn":[0.587623235],"iteration":528,"passed_time":3.751566816,"remaining_time":3.34024191},
{"learn":[0.5869406306],"iteration":529,"passed_time":3.76000426,"remaining_time":3.3343434},
{"learn":[0.5858204258],"iteration":530,"passed_time":3.769560589,"remaining_time":3.329423571},
{"learn":[0.5844630031],"iteration":531,"passed_time":3.777071916,"remaining_time":3.322687324},
{"learn":[0.5838586365],"iteration":532,"passed_time":3.785182853,"remaining_time":3.316473532},
{"learn":[0.5835247052],"iteration":533,"passed_time":3.793206329,"remaining_time":3.31017631},
{"learn":[0.5825480486],"iteration":534,"passed_time":3.802029231,"remaining_time":3.304567462},
{"learn":[0.5817768345],"iteration":535,"passed_time":3.809180965,"remaining_time":3.29749994},
{"learn":[0.5809869502],"iteration":536,"passed_time":3.819096447,"remaining_time":3.292815},
{"learn":[0.5805706153],"iteration":537,"passed_time":3.826820382,"remaining_time":3.286228655},
{"learn":[0.5793807994],"iteration":538,"passed_time":3.836794686,"remaining_time":3.281562802},
{"learn":[0.5783665903],"iteration":539,"passed_time":3.84642811,"remaining_time":3.276586909},
{"learn":[0.5778129914],"iteration":540,"passed_time":3.857685223,"remaining_time":3.272971381},
{"learn":[0.5770000327],"iteration":541,"passed_time":3.86847278,"remaining_time":3.268930874},
{"learn":[0.5760356545],"iteration":542,"passed_time":3.880988861,"remaining_time":3.266320276},
{"learn":[0.575224513],"iteration":543,"passed_time":3.891308764,"remaining_time":3.261832346},
{"learn":[0.5735255053],"iteration":544,"passed_time":3.905271034,"remaining_time":3.26036389},
{"learn":[0.5723241828],"iteration":545,"passed_time":3.919221496,"remaining_time":3.258839852},
{"learn":[0.5713804618],"iteration":546,"passed_time":3.9282087,"remaining_time":3.253160039},
{"learn":[0.5705686087],"iteration":547,"passed_time":3.937679616,"remaining_time":3.247867128},
{"learn":[0.5694039583],"iteration":548,"passed_time":3.949566709,"remaining_time":3.244543872},
{"learn":[0.5690171714],"iteration":549,"passed_time":3.963411982,"remaining_time":3.242791621},
{"learn":[0.5680459926],"iteration":550,"passed_time":3.972647619,"remaining_time":3.237239166},
{"learn":[0.5673459033],"iteration":551,"passed_time":3.983848563,"remaining_time":3.233268399},
{"learn":[0.5664782267],"iteration":552,"passed_time":3.992698497,"remaining_time":3.227371118},
{"learn":[0.5653672321],"iteration":553,"passed_time":4.00084723,"remaining_time":3.220898672},
{"learn":[0.5644003028],"iteration":554,"passed_time":4.010245845,"remaining_time":3.215422344},
{"learn":[0.5629151186],"iteration":555,"passed_time":4.016305025,"remaining_time":3.207265164},
{"learn":[0.5623702836],"iteration":556,"passed_time":4.024407209,"remaining_time":3.200740383},
{"learn":[0.5613918105],"iteration":557,"passed_time":4.031228589,"remaining_time":3.193195405},
{"learn":[0.5602729808],"iteration":558,"passed_time":4.036093189,"remaining_time":3.184109296},
{"learn":[0.5592107326],"iteration":559,"passed_time":4.044048663,"remaining_time":3.177466807},
{"learn":[0.5590014133],"iteration":560,"passed_time":4.049983306,"remaining_time":3.169238273},
{"learn":[0.5580174695],"iteration":561,"passed_time":4.057630694,"remaining_time":3.162352747},
{"learn":[0.5570847671],"iteration":562,"passed_time":4.063197021,"remaining_time":3.153849198},
{"learn":[0.5563084765],"iteration":563,"passed_time":4.067986712,"remaining_time":3.144755685},
{"learn":[0.5551257196],"iteration":564,"passed_time":4.074899257,"remaining_time":3.137311817},
{"learn":[0.5544732443],"iteration":565,"passed_time":4.079191929,"remaining_time":3.127860949},
{"learn":[0.5535507739],"iteration":566,"passed_time":4.083018583,"remaining_time":3.118072392},
{"learn":[0.5532080298],"iteration":567,"passed_time":4.088970802,"remaining_time":3.109921455},
{"learn":[0.5526198922],"iteration":568,"passed_time":4.092920082,"remaining_time":3.100261082},
{"learn":[0.5519738527],"iteration":569,"passed_time":4.096999329,"remaining_time":3.090718792},
{"learn":[0.551604471],"iteration":570,"passed_time":4.103271645,"remaining_time":3.08284332},
{"learn":[0.5506393862],"iteration":571,"passed_time":4.11001054,"remaining_time":3.075322572},
{"learn":[0.5498344015],"iteration":572,"passed_time":4.114561354,"remaining_time":3.066173993},
{"learn":[0.5489328726],"iteration":573,"passed_time":4.121001531,"remaining_time":3.058443645},
{"learn":[0.5480205788],"iteration":574,"passed_time":4.125563035,"remaining_time":3.0493292},
{"learn":[0.5471807914],"iteration":575,"passed_time":4.130195326,"remaining_time":3.040282671},
{"learn":[0.5464418988],"iteration":576,"passed_time":4.138315678,"remaining_time":3.033808547},
{"learn":[0.5456806207],"iteration":577,"passed_time":4.145263873,"remaining_time":3.026472932},
{"learn":[0.5442888442],"iteration":578,"passed_time":4.153223272,"remaining_time":3.019873916},
{"learn":[0.5430850718],"iteration":579,"passed_time":4.160870223,"remaining_time":3.013043955},
{"learn":[0.5424472144],"iteration":580,"passed_time":4.170689446,"remaining_time":3.007777759},
{"learn":[0.5416611652],"iteration":581,"passed_time":4.17928363,"remaining_time":3.001616078},
{"learn":[0.5406485192],"iteration":582,"passed_time":4.188338163,"remaining_time":2.995775324},
{"learn":[0.5401861872],"iteration":583,"passed_time":4.196048596,"remaining_time":2.988966123},
{"learn":[0.5392859206],"iteration":584,"passed_time":4.205782878,"remaining_time":2.983589563},
{"learn":[0.5379542292],"iteration":585,"passed_time":4.218174364,"remaining_time":2.980075404},
{"learn":[0.5368904233],"iteration":586,"passed_time":4.228300741,"remaining_time":2.974937319},
{"learn":[0.5360783435],"iteration":587,"passed_time":4.237113467,"remaining_time":2.968861817},
{"learn":[0.5358120445],"iteration":588,"passed_time":4.245218839,"remaining_time":2.962283434},
{"learn":[0.5349101704],"iteration":589,"passed_time":4.255695245,"remaining_time":2.957347543},
{"learn":[0.5345245825],"iteration":590,"passed_time":4.261079015,"remaining_time":2.948868557},
{"learn":[0.5337837162],"iteration":591,"passed_time":4.270391247,"remaining_time":2.943107481},
{"learn":[0.5334748214],"iteration":592,"passed_time":4.280471942,"remaining_time":2.937861856},
{"learn":[0.5323878823],"iteration":593,"passed_time":4.288883697,"remaining_time":2.931459227},
{"learn":[0.5314206979],"iteration":594,"passed_time":4.297920026,"remaining_time":2.925474976},
{"learn":[0.5308522589],"iteration":595,"passed_time":4.304314592,"remaining_time":2.917689757},
{"learn":[0.5305405282],"iteration":596,"passed_time":4.311338058,"remaining_time":2.910333731},
{"learn":[0.5298931327],"iteration":597,"passed_time":4.318361945,"remaining_time":2.9029791},
{"learn":[0.529225593],"iteration":598,"passed_time":4.325076864,"remaining_time":2.895418735},
{"learn":[0.5285645128],"iteration":599,"passed_time":4.333339826,"remaining_time":2.888893218},
{"learn":[0.5279019893],"iteration":600,"passed_time":4.339831665,"remaining_time":2.881186081},
{"learn":[0.5265465661],"iteration":601,"passed_time":4.347593597,"remaining_time":2.874322677},
{"learn":[0.5256271044],"iteration":602,"passed_time":4.353811004,"remaining_time":2.866439418},
{"learn":[0.5243943072],"iteration":603,"passed_time":4.360539516,"remaining_time":2.858896769},
{"learn":[0.5239753861],"iteration":604,"passed_time":4.367966906,"remaining_time":2.851813104},
{"learn":[0.5232098185],"iteration":605,"passed_time":4.373886962,"remaining_time":2.843748289},
{"learn":[0.5223149705],"iteration":606,"passed_time":4.382030386,"remaining_time":2.837130052},
{"learn":[0.5211280872],"iteration":607,"passed_time":4.388140426,"remaining_time":2.829195801},
{"learn":[0.5203864739],"iteration":608,"passed_time":4.395691553,"remaining_time":2.822192771},
{"learn":[0.519848188],"iteration":609,"passed_time":4.401262009,"remaining_time":2.813921612},
{"learn":[0.5190540502],"iteration":610,"passed_time":4.407743556,"remaining_time":2.806239351},
{"learn":[0.5184285748],"iteration":611,"passed_time":4.413518488,"remaining_time":2.798113028},
{"learn":[0.5174704636],"iteration":612,"passed_time":4.419683772,"remaining_time":2.790240815},
{"learn":[0.5170554281],"iteration":613,"passed_time":4.427830965,"remaining_time":2.783620118},
{"learn":[0.5169160301],"iteration":614,"passed_time":4.43275921,"remaining_time":2.774979343},
{"learn":[0.5167059573],"iteration":615,"passed_time":4.437934337,"remaining_time":2.766504522},
{"learn":[0.5161508637],"iteration":616,"passed_time":4.444357238,"remaining_time":2.758814947},
{"learn":[0.5152107708],"iteration":617,"passed_time":4.449484553,"remaining_time":2.75032864},
{"learn":[0.5147337527],"iteration":618,"passed_time":4.456346341,"remaining_time":2.742920769},
{"learn":[0.5145095766],"iteration":619,"passed_time":4.461504657,"remaining_time":2.734470596},
{"learn":[0.5136866653],"iteration":620,"passed_time":4.466570682,"remaining_time":2.725974699},
{"learn":[0.5133101782],"iteration":621,"passed_time":4.472925344,"remaining_time":2.718272958},
{"learn":[0.5123479527],"iteration":622,"passed_time":4.479765867,"remaining_time":2.710869554},
{"learn":[0.5117347477],"iteration":623,"passed_time":4.484717221,"remaining_time":2.702329607},
{"learn":[0.5100832793],"iteration":624,"passed_time":4.49171582,"remaining_time":2.695029492},
{"learn":[0.5095722858],"iteration":625,"passed_time":4.498296383,"remaining_time":2.687480587},
{"learn":[0.5090247735],"iteration":626,"passed_time":4.505072077,"remaining_time":2.680050853},
{"learn":[0.5089059334],"iteration":627,"passed_time":4.50976131,"remaining_time":2.671387273},
{"learn":[0.5085499493],"iteration":628,"passed_time":4.514710702,"remaining_time":2.662889778},
{"learn":[0.5073379112],"iteration":629,"passed_time":4.521123089,"remaining_time":2.655262766},
{"learn":[0.507218154],"iteration":630,"passed_time":4.527004289,"remaining_time":2.647328974},
{"learn":[0.5069949755],"iteration":631,"passed_time":4.531537833,"remaining_time":2.638616966},
{"learn":[0.5065211244],"iteration":632,"passed_time":4.538606036,"remaining_time":2.631387702},
{"learn":[0.5056706627],"iteration":633,"passed_time":4.543256647,"remaining_time":2.622763301},
{"learn":[0.5054092362],"iteration":634,"passed_time":4.548146646,"remaining_time":2.614289017},
{"learn":[0.5051541012],"iteration":635,"passed_time":4.554987454,"remaining_time":2.606942505},
{"learn":[0.5049082752],"iteration":636,"passed_time":4.559992728,"remaining_time":2.598551586},
{"learn":[0.5041665388],"iteration":637,"passed_time":4.565092453,"remaining_time":2.590224872},
{"learn":[0.504016236],"iteration":638,"passed_time":4.572091032,"remaining_time":2.582981006},
{"learn":[0.5033468743],"iteration":639,"passed_time":4.577851083,"remaining_time":2.575041234},
{"learn":[0.50312055],"iteration":640,"passed_time":4.583908113,"remaining_time":2.56727459},
{"learn":[0.5027146395],"iteration":641,"passed_time":4.589693399,"remaining_time":2.55936174},
{"learn":[0.5018732406],"iteration":642,"passed_time":4.595076801,"remaining_time":2.551232376},
{"learn":[0.5014403149],"iteration":643,"passed_time":4.60271547,"remaining_time":2.544358241},
{"learn":[0.5010535189],"iteration":644,"passed_time":4.61140394,"remaining_time":2.538059533},
{"learn":[0.5007654003],"iteration":645,"passed_time":4.621481999,"remaining_time":2.532514903},
{"learn":[0.5002660015],"iteration":646,"passed_time":4.626561456,"remaining_time":2.524229048},
{"learn":[0.4999691361],"iteration":647,"passed_time":4.635199448,"remaining_time":2.51788612},
{"learn":[0.4985040027],"iteration":648,"passed_time":4.64340728,"remaining_time":2.511303475},
{"learn":[0.4977570393],"iteration":649,"passed_time":4.651109361,"remaining_time":2.504443502},
{"learn":[0.4969930841],"iteration":650,"passed_time":4.657085317,"remaining_time":2.496655569},
{"learn":[0.4968983294],"iteration":651,"passed_time":4.663317952,"remaining_time":2.489010195},
{"learn":[0.4967128532],"iteration":652,"passed_time":4.670069148,"remaining_time":2.481644708},
{"learn":[0.4958047475],"iteration":653,"passed_time":4.675621286,"remaining_time":2.473646735},
{"learn":[0.495152439],"iteration":654,"passed_time":4.683448603,"remaining_time":2.466854608},
{"learn":[0.4950077389],"iteration":655,"passed_time":4.689232802,"remaining_time":2.458987933},
{"learn":[0.4938416322],"iteration":656,"passed_time":4.696392041,"remaining_time":2.451845464},
{"learn":[0.4930717555],"iteration":657,"passed_time":4.702939698,"remaining_time":2.444385071},
{"learn":[0.4920072827],"iteration":658,"passed_time":4.708063316,"remaining_time":2.436190578},
{"learn":[0.4907165005],"iteration":659,"passed_time":4.713714532,"remaining_time":2.428277183},
{"learn":[0.4894825948],"iteration":660,"passed_time":4.717718728,"remaining_time":2.419525944},
{"learn":[0.4887380787],"iteration":661,"passed_time":4.721654725,"remaining_time":2.410754225},
{"learn":[0.4880794],"iteration":662,"passed_time":4.726785458,"remaining_time":2.402604373},
{"learn":[0.4869239131],"iteration":663,"passed_time":4.731346119,"remaining_time":2.394175145},
{"learn":[0.4866644996],"iteration":664,"passed_time":4.73688436,"remaining_time":2.386250016},
{"learn":[0.4859930137],"iteration":665,"passed_time":4.741858821,"remaining_time":2.378049319},
{"learn":[0.4848474216],"iteration":666,"passed_time":4.753465519,"remaining_time":2.373169442},
{"learn":[0.484581385],"iteration":667,"passed_time":4.76527542,"remaining_time":2.368370419},
{"learn":[0.4841107071],"iteration":668,"passed_time":4.781465681,"remaining_time":2.365717699},
{"learn":[0.4835285166],"iteration":669,"passed_time":4.797027802,"remaining_time":2.362715186},
{"learn":[0.4828549555],"iteration":670,"passed_time":4.812418082,"remaining_time":2.359590982},
{"learn":[0.4823627768],"iteration":671,"passed_time":4.827249284,"remaining_time":2.356157388},
{"learn":[0.4821022186],"iteration":672,"passed_time":4.838233664,"remaining_time":2.350820815},
{"learn":[0.4814357265],"iteration":673,"passed_time":4.850852537,"remaining_time":2.346258052},
{"learn":[0.4808665764],"iteration":674,"passed_time":4.865259352,"remaining_time":2.342532281},
{"learn":[0.4796836362],"iteration":675,"passed_time":4.881763863,"remaining_time":2.339780313},
{"learn":[0.4793798677],"iteration":676,"passed_time":4.908777809,"remaining_time":2.34200182},
{"learn":[0.4790119793],"iteration":677,"passed_time":4.91698365,"remaining_time":2.335204624},
{"learn":[0.4783956298],"iteration":678,"passed_time":4.927518435,"remaining_time":2.329504297},
{"learn":[0.4779629024],"iteration":679,"passed_time":4.942796482,"remaining_time":2.326021874},
{"learn":[0.4775785321],"iteration":680,"passed_time":4.957528379,"remaining_time":2.322248977},
{"learn":[0.4768973062],"iteration":681,"passed_time":4.974813838,"remaining_time":2.319634605},
{"learn":[0.4761779806],"iteration":682,"passed_time":4.981081972,"remaining_time":2.311863814},
{"learn":[0.4757221312],"iteration":683,"passed_time":4.988424419,"remaining_time":2.304593737},
{"learn":[0.4756263656],"iteration":684,"passed_time":4.992615951,"remaining_time":2.295874489},
{"learn":[0.4745004284],"iteration":685,"passed_time":4.99665757,"remaining_time":2.287099821},
{"learn":[0.4733769366],"iteration":686,"passed_time":5.004186585,"remaining_time":2.279927804},
{"learn":[0.4726598702],"iteration":687,"passed_time":5.008100707,"remaining_time":2.271115437},
{"learn":[0.4724881769],"iteration":688,"passed_time":5.011909408,"remaining_time":2.262269704},
{"learn":[0.4721290498],"iteration":689,"passed_time":5.018732412,"remaining_time":2.254792823},
{"learn":[0.4715329485],"iteration":690,"passed_time":5.022723299,"remaining_time":2.246051374},
{"learn":[0.4709232342],"iteration":691,"passed_time":5.026654434,"remaining_time":2.23729706},
{"learn":[0.4702156967],"iteration":692,"passed_time":5.034268109,"remaining_time":2.230188037},
{"learn":[0.4692951532],"iteration":693,"passed_time":5.038310761,"remaining_time":2.221503015},
{"learn":[0.4681655718],"iteration":694,"passed_time":5.042174815,"remaining_time":2.212752976},
{"learn":[0.4676259833],"iteration":695,"passed_time":5.046982204,"remaining_time":2.204429009},
{"learn":[0.4672914551],"iteration":696,"passed_time":5.052504164,"remaining_time":2.19642577},
{"learn":[0.4664248181],"iteration":697,"passed_time":5.056591574,"remaining_time":2.187808962},
{"learn":[0.4654152995],"iteration":698,"passed_time":5.061158665,"remaining_time":2.179411671},
{"learn":[0.4645871187],"iteration":699,"passed_time":5.067938522,"remaining_time":2.171973652},
{"learn":[0.4636129727],"iteration":700,"passed_time":5.073460707,"remaining_time":2.164001072},
{"learn":[0.4629021196],"iteration":701,"passed_time":5.077441835,"remaining_time":2.155381292},
{"learn":[0.4624356509],"iteration":702,"passed_time":5.084070128,"remaining_time":2.14789307},
{"learn":[0.4616898587],"iteration":703,"passed_time":5.087932084,"remaining_time":2.139244172},
{"learn":[0.461502723],"iteration":704,"passed_time":5.091682676,"remaining_time":2.130562255},
{"learn":[0.4607064913],"iteration":705,"passed_time":5.097898411,"remaining_time":2.122920868},
{"learn":[0.4601264838],"iteration":706,"passed_time":5.101821765,"remaining_time":2.11433349},
{"learn":[0.4594967183],"iteration":707,"passed_time":5.10571526,"remaining_time":2.105746972},
{"learn":[0.4587125857],"iteration":708,"passed_time":5.109606791,"remaining_time":2.097172886},
{"learn":[0.4578436199],"iteration":709,"passed_time":5.115606428,"remaining_time":2.089473048},
{"learn":[0.4570581987],"iteration":710,"passed_time":5.119512212,"remaining_time":2.080926905},
{"learn":[0.4563754083],"iteration":711,"passed_time":5.123402661,"remaining_time":2.072387593},
{"learn":[0.455734282],"iteration":712,"passed_time":5.129370549,"remaining_time":2.064697542},
{"learn":[0.4552346344],"iteration":713,"passed_time":5.134119039,"remaining_time":2.056523873},
{"learn":[0.4548407667],"iteration":714,"passed_time":5.13799684,"remaining_time":2.048012726},
{"learn":[0.4546658498],"iteration":715,"passed_time":5.142432471,"remaining_time":2.039735785},
{"learn":[0.4536787784],"iteration":716,"passed_time":5.149980592,"remaining_time":2.032698058},
{"learn":[0.4531656475],"iteration":717,"passed_time":5.161283327,"remaining_time":2.027133563},
{"learn":[0.4522545931],"iteration":718,"passed_time":5.169174659,"remaining_time":2.02021986},
{"learn":[0.4515319897],"iteration":719,"passed_time":5.178906477,"remaining_time":2.014019186},
{"learn":[0.4508912132],"iteration":720,"passed_time":5.186648884,"remaining_time":2.007038889},
{"learn":[0.4505330955],"iteration":721,"passed_time":5.19950025,"remaining_time":2.002023642},
{"learn":[0.45014846],"iteration":722,"passed_time":5.204434304,"remaining_time":1.993953392},
{"learn":[0.4496230798],"iteration":723,"passed_time":5.213136137,"remaining_time":1.987328141},
{"learn":[0.4489714995],"iteration":724,"passed_time":5.219591538,"remaining_time":1.979845066},
{"learn":[0.447760626],"iteration":725,"passed_time":5.231064536,"remaining_time":1.974258516},
{"learn":[0.4472187612],"iteration":726,"passed_time":5.236861111,"remaining_time":1.966524186},
{"learn":[0.4467254862],"iteration":727,"passed_time":5.244781026,"remaining_time":1.959588515},
{"learn":[0.4461292088],"iteration":728,"passed_time":5.248854716,"remaining_time":1.95122034},
{"learn":[0.4460194015],"iteration":729,"passed_time":5.252666733,"remaining_time":1.942767148},
{"learn":[0.4456381404],"iteration":730,"passed_time":5.260969512,"remaining_time":1.935979205},
{"learn":[0.44517907],"iteration":731,"passed_time":5.26665731,"remaining_time":1.928229725},
{"learn":[0.4444456942],"iteration":732,"passed_time":5.271278595,"remaining_time":1.920097387},
{"learn":[0.4440187871],"iteration":733,"passed_time":5.281164111,"remaining_time":1.913882362},
{"learn":[0.4435271464],"iteration":734,"passed_time":5.285200343,"remaining_time":1.905548423},
{"learn":[0.4430733229],"iteration":735,"passed_time":5.291710004,"remaining_time":1.898113371},
{"learn":[0.4425361475],"iteration":736,"passed_time":5.29563941,"remaining_time":1.889760061},
{"learn":[0.4424464591],"iteration":737,"passed_time":5.299402747,"remaining_time":1.881359783},
{"learn":[0.441798744],"iteration":738,"passed_time":5.305225227,"remaining_time":1.873699302},
{"learn":[0.4409964408],"iteration":739,"passed_time":5.309220916,"remaining_time":1.865401944},
{"learn":[0.4403560813],"iteration":740,"passed_time":5.313123839,"remaining_time":1.857083771},
{"learn":[0.4402082443],"iteration":741,"passed_time":5.317274863,"remaining_time":1.848863766},
{"learn":[0.4394058233],"iteration":742,"passed_time":5.323246721,"remaining_time":1.841284532},
{"learn":[0.4389634092],"iteration":743,"passed_time":5.327118765,"remaining_time":1.832987102},
{"learn":[0.4382297661],"iteration":744,"passed_time":5.331069716,"remaining_time":1.82472856},
{"learn":[0.4378509109],"iteration":745,"passed_time":5.336889857,"remaining_time":1.817117994},
{"learn":[0.4373704312],"iteration":746,"passed_time":5.341550574,"remaining_time":1.809119538},
{"learn":[0.4368419065],"iteration":747,"passed_time":5.345428683,"remaining_time":1.800866348},
{"learn":[0.4359376797],"iteration":748,"passed_time":5.349650058,"remaining_time":1.792739873},
{"learn":[0.4353610193],"iteration":749,"passed_time":5.355668565,"remaining_time":1.785222855},
{"learn":[0.43480262],"iteration":750,"passed_time":5.359612653,"remaining_time":1.777022038},
{"learn":[0.4338611123],"iteration":751,"passed_time":5.363665093,"remaining_time":1.768868275},
{"learn":[0.4330919158],"iteration":752,"passed_time":5.370012268,"remaining_time":1.761478128},
{"learn":[0.4324355662],"iteration":753,"passed_time":5.375244947,"remaining_time":1.753727131},
{"learn":[0.4320956257],"iteration":754,"passed_time":5.379339882,"remaining_time":1.745613604},
{"learn":[0.4318407706],"iteration":755,"passed_time":5.385381235,"remaining_time":1.738138917},
{"learn":[0.4310733094],"iteration":756,"passed_time":5.389398613,"remaining_time":1.730018313},
{"learn":[0.4304414258],"iteration":757,"passed_time":5.393205081,"remaining_time":1.7218412},
{"learn":[0.4301940002],"iteration":758,"passed_time":5.397023444,"remaining_time":1.713679381},
{"learn":[0.4295671248],"iteration":759,"passed_time":5.403985031,"remaining_time":1.706521589},
{"learn":[0.4287138398],"iteration":760,"passed_time":5.408022695,"remaining_time":1.698446024},
{"learn":[0.4277060871],"iteration":761,"passed_time":5.411910647,"remaining_time":1.690334297},
{"learn":[0.4276329049],"iteration":762,"passed_time":5.419106585,"remaining_time":1.683261154},
{"learn":[0.4272120374],"iteration":763,"passed_time":5.423116273,"remaining_time":1.675203456},
{"learn":[0.4262170338],"iteration":764,"passed_time":5.427087997,"remaining_time":1.667144679},
{"learn":[0.4260307804],"iteration":765,"passed_time":5.432995412,"remaining_time":1.659687893},
{"learn":[0.424911463],"iteration":766,"passed_time":5.437021482,"remaining_time":1.651663632},
{"learn":[0.4244527606],"iteration":767,"passed_time":5.440987093,"remaining_time":1.643631518},
{"learn":[0.423957231],"iteration":768,"passed_time":5.444891763,"remaining_time":1.635591674},
{"learn":[0.4231243814],"iteration":769,"passed_time":5.450741388,"remaining_time":1.628143532},
{"learn":[0.4226545778],"iteration":770,"passed_time":5.454672913,"remaining_time":1.620129828},
{"learn":[0.4219176024],"iteration":771,"passed_time":5.4586728,"remaining_time":1.612146889},
{"learn":[0.4213037995],"iteration":772,"passed_time":5.465075506,"remaining_time":1.604879871},
{"learn":[0.4205828897],"iteration":773,"passed_time":5.470582701,"remaining_time":1.597353605},
{"learn":[0.4198241089],"iteration":774,"passed_time":5.474510484,"remaining_time":1.589374011},
{"learn":[0.4196174672],"iteration":775,"passed_time":5.481331096,"remaining_time":1.582239904},
{"learn":[0.4190959302],"iteration":776,"passed_time":5.486436364,"remaining_time":1.574614297},
{"learn":[0.4182846171],"iteration":777,"passed_time":5.491564322,"remaining_time":1.567001645},
{"learn":[0.4180489042],"iteration":778,"passed_time":5.4987901,"remaining_time":1.559990516},
{"learn":[0.4173703192],"iteration":779,"passed_time":5.502990335,"remaining_time":1.552125479},
{"learn":[0.4173115799],"iteration":780,"passed_time":5.507172544,"remaining_time":1.544264772},
{"learn":[0.4170892268],"iteration":781,"passed_time":5.513541411,"remaining_time":1.537023053},
{"learn":[0.4167629614],"iteration":782,"passed_time":5.51757455,"remaining_time":1.529136242},
{"learn":[0.4163096113],"iteration":783,"passed_time":5.521567332,"remaining_time":1.521248143},
{"learn":[0.4161431439],"iteration":784,"passed_time":5.525414571,"remaining_time":1.513330105},
{"learn":[0.4157729948],"iteration":785,"passed_time":5.531405894,"remaining_time":1.506006185},
{"learn":[0.4156332479],"iteration":786,"passed_time":5.535274106,"remaining_time":1.498111035},
{"learn":[0.4148094529],"iteration":787,"passed_time":5.539452428,"remaining_time":1.490309536},
{"learn":[0.4141926227],"iteration":788,"passed_time":5.545060918,"remaining_time":1.482899688},
{"learn":[0.4133838245],"iteration":789,"passed_time":5.549072152,"remaining_time":1.475069812},
{"learn":[0.4128581363],"iteration":790,"passed_time":5.553012966,"remaining_time":1.467230986},
{"learn":[0.4124350195],"iteration":791,"passed_time":5.556913238,"remaining_time":1.459391356},
{"learn":[0.4121886216],"iteration":792,"passed_time":5.563194908,"remaining_time":1.452183286},
{"learn":[0.411428394],"iteration":793,"passed_time":5.567235547,"remaining_time":1.444396124},
{"learn":[0.4113434814],"iteration":794,"passed_time":5.57116005,"remaining_time":1.436588441},
{"learn":[0.4107073191],"iteration":795,"passed_time":5.577292381,"remaining_time":1.429356339},
{"learn":[0.4104515434],"iteration":796,"passed_time":5.582598685,"remaining_time":1.421916604},
{"learn":[0.409697911],"iteration":797,"passed_time":5.586496576,"remaining_time":1.4141257},
{"learn":[0.4091610675],"iteration":798,"passed_time":5.592266025,"remaining_time":1.406815358},
{"learn":[0.4089148485],"iteration":799,"passed_time":5.597190008,"remaining_time":1.399297502},
{"learn":[0.4081164623],"iteration":800,"passed_time":5.60110084,"remaining_time":1.391534416},
{"learn":[0.4078143337],"iteration":801,"passed_time":5.604991184,"remaining_time":1.383775878},
{"learn":[0.4075121153],"iteration":802,"passed_time":5.611065546,"remaining_time":1.37656278},
{"learn":[0.4066543511],"iteration":803,"passed_time":5.614995268,"remaining_time":1.368829692},
{"learn":[0.4061262759],"iteration":804,"passed_time":5.618899387,"remaining_time":1.361099852},
{"learn":[0.4057383683],"iteration":805,"passed_time":5.624735681,"remaining_time":1.353844568},
{"learn":[0.405098668],"iteration":806,"passed_time":5.629192029,"remaining_time":1.346262778},
{"learn":[0.4048103464],"iteration":807,"passed_time":5.633077365,"remaining_time":1.338553037},
{"learn":[0.4042627427],"iteration":808,"passed_time":5.637155858,"remaining_time":1.330898355},
{"learn":[0.4038146457],"iteration":809,"passed_time":5.642839935,"remaining_time":1.323629121},
{"learn":[0.4035882753],"iteration":810,"passed_time":5.646670918,"remaining_time":1.31593194},
{"learn":[0.4029524912],"iteration":811,"passed_time":5.650522204,"remaining_time":1.308248983},
{"learn":[0.4023803816],"iteration":812,"passed_time":5.660215103,"remaining_time":1.301919095},
{"learn":[0.4022544479],"iteration":813,"passed_time":5.664140136,"remaining_time":1.294262979},
{"learn":[0.4014741791],"iteration":814,"passed_time":5.669615652,"remaining_time":1.28696797},
{"learn":[0.4009087713],"iteration":815,"passed_time":5.678448973,"remaining_time":1.280434572},
{"learn":[0.4001814503],"iteration":816,"passed_time":5.682451633,"remaining_time":1.272813524},
{"learn":[0.3998011069],"iteration":817,"passed_time":5.6887711,"remaining_time":1.265716797},
{"learn":[0.3994006639],"iteration":818,"passed_time":5.692848915,"remaining_time":1.258126561},
{"learn":[0.3988249052],"iteration":819,"passed_time":5.696773027,"remaining_time":1.250511152},
{"learn":[0.3983863013],"iteration":820,"passed_time":5.703115342,"remaining_time":1.243431969},
{"learn":[0.3982359314],"iteration":821,"passed_time":5.707650922,"remaining_time":1.235963338},
{"learn":[0.3981183255],"iteration":822,"passed_time":5.711493912,"remaining_time":1.228352883},
{"learn":[0.3974881912],"iteration":823,"passed_time":5.715424119,"remaining_time":1.2207702},
{"learn":[0.3971166339],"iteration":824,"passed_time":5.721978698,"remaining_time":1.213753057},
{"learn":[0.3965310835],"iteration":825,"passed_time":5.725831041,"remaining_time":1.206167798},
{"learn":[0.3962912006],"iteration":826,"passed_time":5.72966504,"remaining_time":1.198587729},
{"learn":[0.3958290031],"iteration":827,"passed_time":5.735575297,"remaining_time":1.191448009},
{"learn":[0.395536877],"iteration":828,"passed_time":5.739560288,"remaining_time":1.183914125},
{"learn":[0.3948220734],"iteration":829,"passed_time":5.743599726,"remaining_time":1.176399944},
{"learn":[0.3941481229],"iteration":830,"passed_time":5.749021799,"remaining_time":1.169175312},
{"learn":[0.3936614095],"iteration":831,"passed_time":5.753526325,"remaining_time":1.161769739},
{"learn":[0.3932922292],"iteration":832,"passed_time":5.7574007,"remaining_time":1.154244798},
{"learn":[0.392662452],"iteration":833,"passed_time":5.761484885,"remaining_time":1.146770373},
{"learn":[0.3922602342],"iteration":834,"passed_time":5.768157247,"remaining_time":1.139815504},
{"learn":[0.3917799874],"iteration":835,"passed_time":5.773182718,"remaining_time":1.132538236},
{"learn":[0.3910829143],"iteration":836,"passed_time":5.777076473,"remaining_time":1.125045956},
{"learn":[0.3905108723],"iteration":837,"passed_time":5.782847106,"remaining_time":1.117925097},
{"learn":[0.3899821883],"iteration":838,"passed_time":5.787167974,"remaining_time":1.110529254},
{"learn":[0.3895332082],"iteration":839,"passed_time":5.791091492,"remaining_time":1.103065046},
{"learn":[0.389018235],"iteration":840,"passed_time":5.79497879,"remaining_time":1.095602411},
{"learn":[0.3881810281],"iteration":841,"passed_time":5.801340659,"remaining_time":1.088612618},
{"learn":[0.3875065581],"iteration":842,"passed_time":5.805384215,"remaining_time":1.081192552},
{"learn":[0.3870939384],"iteration":843,"passed_time":5.809400669,"remaining_time":1.073775479},
{"learn":[0.3865568403],"iteration":844,"passed_time":5.815661035,"remaining_time":1.06677806},
{"learn":[0.3859900235],"iteration":845,"passed_time":5.820570476,"remaining_time":1.05953647},
{"learn":[0.3855875065],"iteration":846,"passed_time":5.824599143,"remaining_time":1.052141285},
{"learn":[0.3851030718],"iteration":847,"passed_time":5.830230218,"remaining_time":1.045041266},
{"learn":[0.384604719],"iteration":848,"passed_time":5.834565516,"remaining_time":1.037714244},
{"learn":[0.3842266188],"iteration":849,"passed_time":5.839211059,"remaining_time":1.03044901},
{"learn":[0.383441683],"iteration":850,"passed_time":5.843136522,"remaining_time":1.023063856},
{"learn":[0.3830673405],"iteration":851,"passed_time":5.850446597,"remaining_time":1.016274761},
{"learn":[0.3826134557],"iteration":852,"passed_time":5.855548396,"remaining_time":1.009103885},
{"learn":[0.3819816014],"iteration":853,"passed_time":5.863200617,"remaining_time":1.002373876},
{"learn":[0.381268082],"iteration":854,"passed_time":5.868976414,"remaining_time":0.9953234854},
{"learn":[0.3807343401],"iteration":855,"passed_time":5.873962202,"remaining_time":0.9881431741},
{"learn":[0.3803943017],"iteration":856,"passed_time":5.883349197,"remaining_time":0.9817023748},
{"learn":[0.3801722926],"iteration":857,"passed_time":5.88839998,"remaining_time":0.9745370596},
{"learn":[0.3796469649],"iteration":858,"passed_time":5.896011428,"remaining_time":0.9677969865},
{"learn":[0.3789852522],"iteration":859,"passed_time":5.901041715,"remaining_time":0.9606346978},
{"learn":[0.3789383132],"iteration":860,"passed_time":5.906250301,"remaining_time":0.9535061462},
{"learn":[0.3781229037],"iteration":861,"passed_time":5.91435702,"remaining_time":0.9468460194},
{"learn":[0.377511115],"iteration":862,"passed_time":5.918356311,"remaining_time":0.939530492},
{"learn":[0.3774335364],"iteration":863,"passed_time":5.922370646,"remaining_time":0.9322250091},
{"learn":[0.3773645202],"iteration":864,"passed_time":5.928312433,"remaining_time":0.925227952},
{"learn":[0.3773066883],"iteration":865,"passed_time":5.932124556,"remaining_time":0.9179037996},
{"learn":[0.3769292064],"iteration":866,"passed_time":5.936013636,"remaining_time":0.9105995543},
{"learn":[0.3764394676],"iteration":867,"passed_time":5.942205032,"remaining_time":0.9036532998},
{"learn":[0.3762018872],"iteration":868,"passed_time":5.946363476,"remaining_time":0.8964023192},
{"learn":[0.3758561675],"iteration":869,"passed_time":5.950244738,"remaining_time":0.8891170298},
{"learn":[0.375562902],"iteration":870,"passed_time":5.954345396,"remaining_time":0.8818720505},
{"learn":[0.3747936437],"iteration":871,"passed_time":5.960150259,"remaining_time":0.8748844416},
{"learn":[0.3741639456],"iteration":872,"passed_time":5.964334822,"remaining_time":0.8676638286},
{"learn":[0.3738822006],"iteration":873,"passed_time":5.969030224,"remaining_time":0.860523808},
{"learn":[0.3733336508],"iteration":874,"passed_time":5.974996852,"remaining_time":0.8535709788},
{"learn":[0.3732521415],"iteration":875,"passed_time":5.980135599,"remaining_time":0.8465032127},
{"learn":[0.3724896895],"iteration":876,"passed_time":5.98410514,"remaining_time":0.8392758635},
{"learn":[0.3720094459],"iteration":877,"passed_time":5.989679597,"remaining_time":0.8322789417},
{"learn":[0.3715989128],"iteration":878,"passed_time":5.994159513,"remaining_time":0.8251345859},
{"learn":[0.371259188],"iteration":879,"passed_time":5.99806819,"remaining_time":0.8179183895},
{"learn":[0.3708865901],"iteration":880,"passed_time":6.002138755,"remaining_time":0.8107315685},
{"learn":[0.3703555847],"iteration":881,"passed_time":6.008374278,"remaining_time":0.8038414567},
{"learn":[0.3699793277],"iteration":882,"passed_time":6.012399194,"remaining_time":0.7966599159},
{"learn":[0.3695595749],"iteration":883,"passed_time":6.016341292,"remaining_time":0.7894746491},
{"learn":[0.3690212408],"iteration":884,"passed_time":6.022122995,"remaining_time":0.7825357565},
{"learn":[0.3687016144],"iteration":885,"passed_time":6.026218628,"remaining_time":0.7753825323},
{"learn":[0.368389651],"iteration":886,"passed_time":6.030188347,"remaining_time":0.7682201615},
{"learn":[0.3679530969],"iteration":887,"passed_time":6.0341745,"remaining_time":0.7610670541},
{"learn":[0.3678141172],"iteration":888,"passed_time":6.040153138,"remaining_time":0.7541698519},
{"learn":[0.3675030944],"iteration":889,"passed_time":6.044023246,"remaining_time":0.7470141091},
{"learn":[0.3673501913],"iteration":890,"passed_time":6.047963165,"remaining_time":0.7398742817},
{"learn":[0.3668244701],"iteration":891,"passed_time":6.053727777,"remaining_time":0.732962556},
{"learn":[0.3661296224],"iteration":892,"passed_time":6.057787702,"remaining_time":0.7258491423},
{"learn":[0.3653032981],"iteration":893,"passed_time":6.061996966,"remaining_time":0.7187602666},
{"learn":[0.364768238],"iteration":894,"passed_time":6.066698647,"remaining_time":0.7117355954},
{"learn":[0.3640873305],"iteration":895,"passed_time":6.077662851,"remaining_time":0.7054430094},
{"learn":[0.3635736588],"iteration":896,"passed_time":6.081937301,"remaining_time":0.6983718417},
{"learn":[0.3629586989],"iteration":897,"passed_time":6.088542445,"remaining_time":0.6915716363},
{"learn":[0.3625601581],"iteration":898,"passed_time":6.092453996,"remaining_time":0.6844692476},
{"learn":[0.3620764985],"iteration":899,"passed_time":6.09645096,"remaining_time":0.67738344},
{"learn":[0.3618151883],"iteration":900,"passed_time":6.102399068,"remaining_time":0.6705188766},
{"learn":[0.3616503332],"iteration":901,"passed_time":6.10629056,"remaining_time":0.663432899},
{"learn":[0.3613912228],"iteration":902,"passed_time":6.110137204,"remaining_time":0.6563491792},
{"learn":[0.3612572561],"iteration":903,"passed_time":6.114212647,"remaining_time":0.6492969182},
{"learn":[0.3605769677],"iteration":904,"passed_time":6.120035132,"remaining_time":0.6424346271},
{"learn":[0.3602734498],"iteration":905,"passed_time":6.123871222,"remaining_time":0.6353685374},
{"learn":[0.359755972],"iteration":906,"passed_time":6.128739508,"remaining_time":0.6284154071},
{"learn":[0.3591911134],"iteration":907,"passed_time":6.134619862,"remaining_time":0.6215694134},
{"learn":[0.358353675],"iteration":908,"passed_time":6.138613924,"remaining_time":0.6145367075},
{"learn":[0.3579695295],"iteration":909,"passed_time":6.142582287,"remaining_time":0.6075081383},
{"learn":[0.3574555335],"iteration":910,"passed_time":6.146506134,"remaining_time":0.6004819385},
{"learn":[0.3570466929],"iteration":911,"passed_time":6.15247492,"remaining_time":0.5936598607},
{"learn":[0.3565791396],"iteration":912,"passed_time":6.156455376,"remaining_time":0.5866501837},
{"learn":[0.3563938202],"iteration":913,"passed_time":6.160510335,"remaining_time":0.5796541453},
{"learn":[0.3555773918],"iteration":914,"passed_time":6.168591486,"remaining_time":0.5730385533},
{"learn":[0.3551342807],"iteration":915,"passed_time":6.175709833,"remaining_time":0.5663314694},
{"learn":[0.3548291699],"iteration":916,"passed_time":6.187707782,"remaining_time":0.5600651537},
{"learn":[0.3543480495],"iteration":917,"passed_time":6.197802047,"remaining_time":0.5536163049},
{"learn":[0.3536906935],"iteration":918,"passed_time":6.208882258,"remaining_time":0.5472464232},
{"learn":[0.3532621825],"iteration":919,"passed_time":6.225387087,"remaining_time":0.5413380076},
{"learn":[0.3526630022],"iteration":920,"passed_time":6.239990724,"remaining_time":0.535243504},
{"learn":[0.3523764468],"iteration":921,"passed_time":6.254112008,"remaining_time":0.529089736},
{"learn":[0.3520037054],"iteration":922,"passed_time":6.268570937,"remaining_time":0.5229468712},
{"learn":[0.3515547579],"iteration":923,"passed_time":6.280221233,"remaining_time":0.5165549932},
{"learn":[0.3513306215],"iteration":924,"passed_time":6.291284167,"remaining_time":0.5101041217},
{"learn":[0.3507849703],"iteration":925,"passed_time":6.305771893,"remaining_time":0.5039169763},
{"learn":[0.3502191074],"iteration":926,"passed_time":6.319683403,"remaining_time":0.4976665463},
{"learn":[0.349595302],"iteration":927,"passed_time":6.332488562,"remaining_time":0.4913137677},
{"learn":[0.3491481061],"iteration":928,"passed_time":6.344366062,"remaining_time":0.4848762006},
{"learn":[0.3486142302],"iteration":929,"passed_time":6.354671792,"remaining_time":0.4783086295},
{"learn":[0.3481296165],"iteration":930,"passed_time":6.368023101,"remaining_time":0.4719587476},
{"learn":[0.3476844228],"iteration":931,"passed_time":6.375803942,"remaining_time":0.4651874121},
{"learn":[0.3473070054],"iteration":932,"passed_time":6.395296364,"remaining_time":0.4592549371},
{"learn":[0.3472785624],"iteration":933,"passed_time":6.402156558,"remaining_time":0.4524007846},
{"learn":[0.3470258632],"iteration":934,"passed_time":6.41231815,"remaining_time":0.4457761281},
{"learn":[0.3464478733],"iteration":935,"passed_time":6.41863263,"remaining_time":0.4388808636},
{"learn":[0.3458850516],"iteration":936,"passed_time":6.429110077,"remaining_time":0.4322667394},
{"learn":[0.3457985758],"iteration":937,"passed_time":6.434981754,"remaining_time":0.4253399454},
{"learn":[0.3450867858],"iteration":938,"passed_time":6.445067165,"remaining_time":0.4186891342},
{"learn":[0.3444536318],"iteration":939,"passed_time":6.451126848,"remaining_time":0.4117740541},
{"learn":[0.343957035],"iteration":940,"passed_time":6.459241441,"remaining_time":0.4049896334},
{"learn":[0.3438453329],"iteration":941,"passed_time":6.464577922,"remaining_time":0.398031337},
{"learn":[0.3437766989],"iteration":942,"passed_time":6.472018018,"remaining_time":0.3912036342},
{"learn":[0.3434949001],"iteration":943,"passed_time":6.486497839,"remaining_time":0.3847922447},
{"learn":[0.3431746013],"iteration":944,"passed_time":6.494804973,"remaining_time":0.3780045222},
{"learn":[0.3428235307],"iteration":945,"passed_time":6.505737966,"remaining_time":0.371363478},
{"learn":[0.3426367642],"iteration":946,"passed_time":6.512928518,"remaining_time":0.3645039192},
{"learn":[0.3421942526],"iteration":947,"passed_time":6.522388509,"remaining_time":0.3577681461},
{"learn":[0.3418694254],"iteration":948,"passed_time":6.52976034,"remaining_time":0.3509144124},
{"learn":[0.3413949167],"iteration":949,"passed_time":6.538338641,"remaining_time":0.3441230864},
{"learn":[0.3410423481],"iteration":950,"passed_time":6.543420927,"remaining_time":0.3371478711},
{"learn":[0.3407098122],"iteration":951,"passed_time":6.549492143,"remaining_time":0.3302264946},
{"learn":[0.3403641486],"iteration":952,"passed_time":6.557915629,"remaining_time":0.3234229114},
{"learn":[0.3400438488],"iteration":953,"passed_time":6.563814947,"remaining_time":0.3164942217},
{"learn":[0.3397019762],"iteration":954,"passed_time":6.575152933,"remaining_time":0.3098239602},
{"learn":[0.3396579056],"iteration":955,"passed_time":6.580756555,"remaining_time":0.3028800088},
{"learn":[0.3393100451],"iteration":956,"passed_time":6.587099062,"remaining_time":0.2959720582},
{"learn":[0.3391266521],"iteration":957,"passed_time":6.591446365,"remaining_time":0.2889778156},
{"learn":[0.3386452774],"iteration":958,"passed_time":6.598432889,"remaining_time":0.2821019275},
{"learn":[0.3383490659],"iteration":959,"passed_time":6.604355749,"remaining_time":0.2751814895},
{"learn":[0.3380183062],"iteration":960,"passed_time":6.608467387,"remaining_time":0.2681896234},
{"learn":[0.3377436745],"iteration":961,"passed_time":6.616081906,"remaining_time":0.2613421127},
{"learn":[0.3375101733],"iteration":962,"passed_time":6.621840061,"remaining_time":0.2544216846},
{"learn":[0.3369505453],"iteration":963,"passed_time":6.627715609,"remaining_time":0.2475080518},
{"learn":[0.3365177582],"iteration":964,"passed_time":6.633826303,"remaining_time":0.2406050991},
{"learn":[0.3359865589],"iteration":965,"passed_time":6.639367596,"remaining_time":0.2336837456},
{"learn":[0.3358526939],"iteration":966,"passed_time":6.645283205,"remaining_time":0.2267780204},
{"learn":[0.3355540392],"iteration":967,"passed_time":6.650546377,"remaining_time":0.2198527728},
{"learn":[0.3352381592],"iteration":968,"passed_time":6.654760565,"remaining_time":0.2128973968},
{"learn":[0.3350893687],"iteration":969,"passed_time":6.662306774,"remaining_time":0.206050725},
{"learn":[0.3347878457],"iteration":970,"passed_time":6.668171406,"remaining_time":0.1991523901},
{"learn":[0.3342575181],"iteration":971,"passed_time":6.672260748,"remaining_time":0.1922050421},
{"learn":[0.3339511346],"iteration":972,"passed_time":6.67829928,"remaining_time":0.1853176573},
{"learn":[0.3335976361],"iteration":973,"passed_time":6.68302589,"remaining_time":0.178396995},
{"learn":[0.3330759944],"iteration":974,"passed_time":6.687686214,"remaining_time":0.1714791337},
{"learn":[0.3328006836],"iteration":975,"passed_time":6.69572111,"remaining_time":0.1646488798},
{"learn":[0.3322582664],"iteration":976,"passed_time":6.701095257,"remaining_time":0.1577535219},
{"learn":[0.3319427655],"iteration":977,"passed_time":6.70526535,"remaining_time":0.1508341899},
{"learn":[0.331395713],"iteration":978,"passed_time":6.713374681,"remaining_time":0.1440049727},
{"learn":[0.3307995517],"iteration":979,"passed_time":6.717924621,"remaining_time":0.1371005025},
{"learn":[0.3302382731],"iteration":980,"passed_time":6.724430363,"remaining_time":0.1302387124},
{"learn":[0.3299064969],"iteration":981,"passed_time":6.730119073,"remaining_time":0.1233626714},
{"learn":[0.3295950965],"iteration":982,"passed_time":6.734307077,"remaining_time":0.1164630929},
{"learn":[0.329122412],"iteration":983,"passed_time":6.738574491,"remaining_time":0.1095703169},
{"learn":[0.3284497753],"iteration":984,"passed_time":6.743719079,"remaining_time":0.1026962296},
{"learn":[0.3280877778],"iteration":985,"passed_time":6.747635437,"remaining_time":0.09580821108},
{"learn":[0.3276627255],"iteration":986,"passed_time":6.751762226,"remaining_time":0.08892898576},
{"learn":[0.3274940839],"iteration":987,"passed_time":6.757913317,"remaining_time":0.08207991883},
{"learn":[0.3272346985],"iteration":988,"passed_time":6.761825512,"remaining_time":0.07520736161},
{"learn":[0.3270079238],"iteration":989,"passed_time":6.765633761,"remaining_time":0.06833973496},
{"learn":[0.3265983433],"iteration":990,"passed_time":6.773813409,"remaining_time":0.06151798252},
{"learn":[0.3261409683],"iteration":991,"passed_time":6.780702044,"remaining_time":0.054683081},
{"learn":[0.3259729311],"iteration":992,"passed_time":6.785088172,"remaining_time":0.04783043022},
{"learn":[0.3254672781],"iteration":993,"passed_time":6.794844015,"remaining_time":0.04101515502},
{"learn":[0.3254209421],"iteration":994,"passed_time":6.799184925,"remaining_time":0.03416675842},
{"learn":[0.3249083807],"iteration":995,"passed_time":6.805453806,"remaining_time":0.02733113978},
{"learn":[0.3245882847],"iteration":996,"passed_time":6.810376011,"remaining_time":0.02049260585},
{"learn":[0.3245042066],"iteration":997,"passed_time":6.814316571,"remaining_time":0.01365594503},
{"learn":[0.3240505525],"iteration":998,"passed_time":6.818911554,"remaining_time":0.006825737291},
{"learn":[0.3236027878],"iteration":999,"passed_time":6.823913988,"remaining_time":0}
]}